Workbook

Sheet Instrucciones
B2: FASE 2 — BASE CONTABLE ANUAL · Matriz empresa–año–ratio
B3: Índice de resiliencia financiera sectorial · Empresas del S&P IPSA · 2017–2025
B5: Leyenda
B6: Celda de ingreso | C6: Datos a extraer de los estados financieros de la CMF. Texto azul sobre fondo amarillo.
B7: Celda calculada | C7: Fórmula automática. No modificar.
B8: Vínculo a otra hoja | C8: Fórmula que trae datos de otra hoja del libro (texto verde).
B9: Campo clave | C9: Empresa, sector y año. Ya vienen completados.
B11: Secuencia de trabajo
B12: Paso 1 | C12: Hoja «Empresas»: registre la moneda de presentación de cada sociedad (CLP o USD) y el precio ajustado de cierre al 31-12-2016, tomado de su archivo de precios de Yahoo Finance.
B13: Paso 2 | C13: Hojas «Captura_NoFin» y «Captura_Fin»: ingrese las partidas de los estados financieros consolidados anuales al 31 de diciembre, en miles de la moneda de presentación, tal como figuran en el documento de la CMF.
B14: Paso 3 | C14: Estrategia de extracción: cada estado financiero anual trae la columna del año y la comparativa del año anterior. Basta con abrir cinco documentos por empresa — ejercicios 2018, 2020, 2022, 2024 y 2025 — para cubrir los nueve años.
B15: Paso 4 | C15: Registre en la columna «fuente» el documento y la columna de donde tomó cada fila (p. ej. «EEFF 2020, comparativo»). Es la trazabilidad que declara su metodología.
B16: Paso 5 | C16: Hojas «Ratios_NoFin» y «Ratios_Fin»: se calculan solas. Revise la hoja «Control» antes de pasar a la Fase 3.
B18: Convenciones
B19: Signos | C19: Ingrese los costos financieros y el gasto en provisiones como números positivos. Las fórmulas usan su valor absoluto, de modo que un signo negativo tampoco produce error.
B20: Moneda | C20: No convierta a pesos. Todos los ratios son cocientes adimensionales y no cambian con la moneda. La conversión solo sería necesaria para variables de tamaño, que este diseño no utiliza.
B21: Sin dato | C21: Deje la celda vacía. Nunca ingrese cero para un dato faltante: un cero se calcula como valor real y sesga el ratio.
B22: EBIT | C22: Se calcula para todas las empresas como Ganancia antes de impuestos + Costos financieros. La columna «resultado operacional presentado» es solo informativa, porque NIC 1 no obliga a presentar ese subtotal.
B23: ROE | C23: Es descriptivo, no entra al KPI. Se deja en blanco cuando el patrimonio de la controladora es cero o negativo (caso Latam 2020–2021).
B24: Bancos | C24: Usan una plantilla propia y se ingresan en millones (MM$), tal como vienen. «Capital de trabajo» no aplica: sus estados no distinguen corriente de no corriente.
B26: Fila de ejemplo — formato esperado (valores ilustrativos, NO son datos reales de ninguna empresa)
B27: Campo | C27: Ejemplo | D27: Formato
B28: activo_corriente | C28: 845320 | D28: Miles de la moneda de presentación, sin puntos ni signo
B29: activo_total | C29: 4120550 | D29: Miles
B30: ingresos | C30: 1985400 | D30: Miles
B31: costos_financieros | C31: 62300 | D31: Positivo, en miles
B32: ganancia_antes_impuestos | C32: 210880 | D32: Puede ser negativo si hubo pérdida
B33: precio_ajustado_cierre | C33: 412,35 | D33: Precio ajustado por dividendos al último día hábil del año
B34: fuente | C34: EEFF 2020, comparativo | D34: Texto libre

Sheet Empresas
A1: N.º | B1: Nemotécnico | C1: Razón social | D1: Sector GICS | E1: Cód. sector | F1: Sector de análisis | G1: Plantilla | H1: Moneda de presentación | I1: Precio ajustado 31-12-2016 | J1: Observaciones
A2: 1 | B2: AGUAS-A | C2: Aguas Andinas S.A., Serie A | D2: Utilities | E2: 1 | F2: Servicios básicos e infraestructura | G2: No financiera | H2: CLP | I2: 191.32983
A3: 2 | B3: COLBUN | C3: Colbún S.A. | D3: Utilities | E3: 1 | F3: Servicios básicos e infraestructura | G3: No financiera | H3: USD | I3: 125.31001
A4: 3 | B4: ENELAM | C4: Enel Américas S.A. | D4: Utilities | E4: 1 | F4: Servicios básicos e infraestructura | G4: No financiera | H4: USD | I4: 104.2692 | J4: USD. Resultados por naturaleza (sin costo de ventas). 2024: ganancia extraordinaria por venta de activos en Perú.
A5: 4 | B5: ENELCHILE | C5: Enel Chile S.A. | D5: Utilities | E5: 1 | F5: Servicios básicos e infraestructura | G5: No financiera | I5: 38.458931
A6: 5 | B6: ECL | C6: Engie Energía Chile S.A. | D6: Utilities | E6: 1 | F6: Servicios básicos e infraestructura | G6: No financiera | H6: USD | I6: 1052.5234 | J6: USD (kUSD en los EEFF).
A7: 6 | B7: ENTEL | C7: Empresa Nacional de Telecomunicaciones S.A. | D7: Communication Services | E7: 1 | F7: Servicios básicos e infraestructura | G7: No financiera | H7: CLP | I7: 3329.6765
A8: 7 | B8: CENCOSUD | C8: Cencosud S.A. | D8: Consumer Staples (verificar) | E8: 2 | F8: Consumo | G8: No financiera | H8: CLP | I8: 1171.8052 | J8: Verificar sector GICS contra archivo de constituyentes de S&P DJI; no afecta la normalización.
A9: 8 | B9: FALABELLA | C9: Falabella S.A. | D9: Consumer Discretionary | E9: 2 | F9: Consumo | G9: No financiera | H9: CLP | I9: 4588.8062
A10: 9 | B10: RIPLEY | C10: Ripley Corp S.A. | D10: Consumer Discretionary | E10: 2 | F10: Consumo | G10: No financiera | H10: CLP | I10: 260.35175
A11: 10 | B11: CCU | C11: Compañía Cervecerías Unidas S.A. | D11: Consumer Staples | E11: 2 | F11: Consumo | G11: No financiera | H11: CLP | I11: 4615.2593
A12: 11 | B12: ANDINA-B | C12: Embotelladora Andina S.A., Serie B | D12: Consumer Staples | E12: 2 | F12: Consumo | G12: No financiera | H12: CLP | I12: 1467.3553
A13: 12 | B13: CONCHATORO | C13: Viña Concha y Toro S.A. | D13: Consumer Staples | E13: 2 | F13: Consumo | G13: No financiera | H13: CLP | I13: 789.89917
A14: 13 | B14: LTM | C14: Latam Airlines Group S.A. | D14: Industrials | E14: 3 | F14: Industria, recursos naturales e inmobiliario | G14: No financiera | H14: USD | I14: 313.14334 | J14: USD. ROE no disponible 2020–2021 por patrimonio negativo (reorganización Capítulo 11).
A15: 14 | B15: PARAUCO | C15: Parque Arauco S.A. | D15: Real Estate | E15: 3 | F15: Industria, recursos naturales e inmobiliario | G15: No financiera | H15: CLP | I15: 1274.4506 | J15: Propiedades de inversión a valor razonable (NIC 40): la utilidad puede incluir revalorizaciones.
A16: 15 | B16: CAP | C16: CAP S.A. | D16: Materials | E16: 3 | F16: Industria, recursos naturales e inmobiliario | G16: No financiera | H16: USD | I16: 2815.3384
A17: 16 | B17: CMPC | C17: Empresas CMPC S.A. | D17: Materials | E17: 3 | F17: Industria, recursos naturales e inmobiliario | G17: No financiera | H17: USD | I17: 1224.226
A18: 17 | B18: SQM-B | C18: Sociedad Química y Minera de Chile S.A., Serie B | D18: Materials | E18: 3 | F18: Industria, recursos naturales e inmobiliario | G18: No financiera | H18: USD | I18: 16181.312 | J18: USD. 2025: revisar perímetro por la sociedad NovaAndino Litio con Codelco.
A19: 18 | B19: COPEC | C19: Empresas Copec S.A. | D19: Energy | E19: 3 | F19: Industria, recursos naturales e inmobiliario | G19: No financiera | H19: USD | I19: 6182.0645
A20: 19 | B20: CHILE | C20: Banco de Chile | D20: Financials | E20: 4 | F20: Financiero (bancos) | G20: Financiera | H20: CLP | I20: 44.933334 | J20: Montos en MM$ (millones), tal como vienen del EEFF bancario.
A21: 20 | B21: BCI | C21: Banco de Crédito e Inversiones | D21: Financials | E21: 4 | F21: Financiero (bancos) | G21: Financiera | H21: CLP | I21: 15494.488 | J21: Montos en MM$ (millones), tal como vienen del EEFF bancario.
A22: 21 | B22: BSANTANDER | C22: Banco Santander-Chile | D22: Financials | E22: 4 | F22: Financiero (bancos) | G22: Financiera | H22: CLP | I22: 22.88047 | J22: Montos en MM$ (millones), tal como vienen del EEFF bancario.
A23: 22 | B23: ITAUCL | C23: Banco Itaú Chile | D23: Financials | E23: 4 | F23: Financiero (bancos) | G23: Financiera | H23: CLP | I23: 17342.992 | J23: Montos en MM$ (millones). Hasta 2021 figura como Itaú Corpbanca.
B25: Excluidas del panel:
B26: MALLPLAZA, SMU, CENCOMALLS — ingresaron al índice con posterioridad a 2017.
B27: IAM — salió en septiembre de 2018 y reingresó en septiembre de 2019.
B28: SALFACORP — salió en junio de 2020 y reingresó en septiembre de 2025.
B29: QUINENCO — registró una salida y reingresó en marzo de 2022.
B30: ILC — salió en septiembre de 2021 y reingresó en marzo de 2025.
B31: VAPORES — vehículo de inversión: la participación en Hapag-Lloyd concentra más del 92% de sus activos.
B32: Criterio: presencia ininterrumpida en el S&P IPSA 2017–2025 (anuncios de rebalanceo de S&P DJI).

Sheet Diccionario
A1: Código | B1: Campo | C1: Partida en los EEFF (CMF) | D1: Elemento taxonomía IFRS | E1: Estado financiero | F1: Condición | G1: Se usa en
A2: P01 | B2: activo_corriente | C2: Total de activos corrientes | D2: ifrs-full:CurrentAssets | E2: Situación financiera | F2: Núcleo | G2: Liquidez; Capital de trabajo
A3: P02 | B3: pasivo_corriente | C3: Total de pasivos corrientes | D3: ifrs-full:CurrentLiabilities | E3: Situación financiera | F3: Núcleo | G3: Liquidez; Capital de trabajo
A4: P03 | B4: activo_total | C4: Total de activos | D4: ifrs-full:Assets | E4: Situación financiera | F4: Núcleo | G4: Capital de trabajo; Rentabilidad; Endeudamiento; Uso de activos
A5: P04 | B5: pasivo_total | C5: Total de pasivos | D5: ifrs-full:Liabilities | E5: Situación financiera | F5: Núcleo | G5: Endeudamiento; control de cuadre
A6: P05 | B6: patrimonio_total | C6: Patrimonio total | D6: ifrs-full:Equity | E6: Situación financiera | F6: Núcleo | G6: Control de cuadre
A7: P06 | B7: ingresos | C7: Ingresos de actividades ordinarias | D7: ifrs-full:Revenue | E7: Resultados | F7: Núcleo | G7: Eficiencia; Uso de activos
A8: P07 | B8: costos_financieros | C8: Costos financieros | D8: ifrs-full:FinanceCosts | E8: Resultados | F8: Núcleo | G8: EBIT; Cobertura
A9: P08 | B9: ganancia_antes_impuestos | C9: Ganancia (pérdida), antes de impuestos | D9: ifrs-full:ProfitLossBeforeTax | E9: Resultados | F9: Núcleo | G9: EBIT
A10: P09 | B10: ganancia_ejercicio | C10: Ganancia (pérdida) | D10: ifrs-full:ProfitLoss | E10: Resultados | F10: Núcleo | G10: Rentabilidad (ROA)
A11: P10 | B11: patrimonio_controladora | C11: Patrimonio atribuible a los propietarios de la controladora | D11: ifrs-full:EquityAttributableToOwnersOfParent | E11: Situación financiera | F11: Opcional | G11: ROE descriptivo
A12: P11 | B12: ganancia_controladora | C12: Ganancia (pérdida), atribuible a los propietarios de la controladora | D12: ifrs-full:ProfitLossAttributableToOwnersOfParent | E12: Resultados | F12: Opcional | G12: ROE descriptivo
... A26: B11 | B26: ganancia_ejercicio | C26: UTILIDAD CONSOLIDADA DEL EJERCICIO | D26: Compendio CMF | E26: Resultados | F26: Núcleo | G26: Rentabilidad (ROA)
A28: P = empresas no financieras (18) · B = bancos (4) · M = dato de mercado, común a ambas. Bancos: montos en MM$, tal como vienen; no convertir.
A29: Bancos: el Compendio de Normas Contables de la CMF se actualizó con vigencia desde 2022. Homologue los rubros de 2021 usando la columna comparativa del EEFF 2022.

Sheet Captura_NoFin
A1: nemotecnico | B1: cod_sector | C1: sector | D1: anio | E1: moneda | F1: activo_corriente | G1: pasivo_corriente | H1: activo_total | I1: pasivo_total | J1: patrimonio_total | K1: ingresos | L1: costos_financieros | M1: ganancia_antes_impuestos | N1: ganancia_ejercicio | O1: patrimonio_controladora | P1: ganancia_controladora | Q1: resultado_operacional_presentado | R1: precio_ajustado_cierre | S1: fuente | T1: observaciones
A2: AGUAS-A | B2: 1 | C2: Servicios básicos e infraestructura | D2: 2017 | E2: =IFERROR(INDEX(Empresas!$H$2:$H$23,MATCH($A2,Empresas!$B$2:$B$23,0))&"","") | F2: 150618761 | G2: 237111903 | H2: 1796880136 | I2: 1103580659 | J2: 693299477 | K2: 509540577 | L2: 31112258 | M2: 189822878 | N2: 143482253 | O2: 642630776 | P2: 139620280 | Q2: 226819054 | R2: 236.90225 | S2: XBRL 2018, comparativo
A3: AGUAS-A | B3: 1 | C3: Servicios básicos e infraestructura | D3: 2018 | E3: =IFERROR(INDEX(Empresas!$H$2:$H$23,MATCH($A3,Empresas!$B$2:$B$23,0))&"","") | F3: 168513972 | G3: 242318524 | H3: 1906052099 | I3: 1219060702 | J3: 686991397 | K3: 530404680 | L3: 29996785 | M3: 185824777 | N3: 139318355 | O3: 638620655 | P3: 136056517 | Q3: 233071676 | R3: 234.73775 | S3: XBRL 2018, actual
A4: AGUAS-A | B4: 1 | C4: Servicios básicos e infraestructura | D4: 2019 | E4: =IFERROR(INDEX(Empresas!$H$2:$H$23,MATCH($A4,Empresas!$B$2:$B$23,0))&"","") | F4: 197676646 | G4: 242137717 | H4: 2001444302 | I4: 1313970839 | J4: 687473463 | K4: 484329084 | L4: 26752209 | M4: 192072838 | N4: 139750372 | O4: 644453334 | P4: 141737188 | Q4: 235636236 | R4: 207.44206 | S4: XBRL 2020, comparativo
A5: AGUAS-A | B5: 1 | C5: Servicios básicos e infraestructura | D5: 2020 | E5: =IFERROR(INDEX(Empresas!$H$2:$H$23,MATCH($A5,Empresas!$B$2:$B$23,0))&"","") | F5: 302254499 | G5: 244032589 | H5: 2144436488 | I5: 1303687681 | J5: 840748807 | K5: 478773563 | L5: 28172393 | M5: 115681631 | N5: 100365495 | O5: 840723242 | P5: 98691668 | Q5: 162824880 | R5: 159.16322 | S5: XBRL 2020, actual
A6: AGUAS-A | B6: 1 | C6: Servicios básicos e infraestructura | D6: 2021 | E6: =IFERROR(INDEX(Empresas!$H$2:$H$23,MATCH($A6,Empresas!$B$2:$B$23,0))&"","") | F6: 283854689 | G6: 248642211 | H6: 2229221610 | I6: 1386673897 | J6: 842547713 | K6: 506459633 | L6: 27862844 | M6: 120309420 | N6: 100646534 | O6: 842520215 | P6: 100644529 | Q6: 212947803 | R6: 118.44007 | S6: XBRL 2022, comparativo
A7: AGUAS-A | B7: 1 | C7: Servicios básicos e infraestructura | D7: 2022 | E7: =IFERROR(INDEX(Empresas!$H$2:$H$23,MATCH($A7,Empresas!$B$2:$B$23,0))&"","") | F7: 324838124 | G7: 265797147 | H7: 2379349560 | I7: 1540458461 | J7: 838891099 | K7: 575465445 | L7: 36630374 | M7: 82672491 | N7: 85250874 | O7: 838861526 | P7: 85248734 | Q7: 228258340 | R7: 160.16978 | S7: XBRL 2022, actual
A8: AGUAS-A | B8: 1 | C8: Servicios básicos e infraestructura | D8: 2023 | E8: =IFERROR(INDEX(Empresas!$H$2:$H$23,MATCH($A8,Empresas!$B$2:$B$23,0))&"","") | F8: 275004410 | G8: 361668126 | H8: 2423347729 | I8: 1537208431 | J8: 886139298 | K8: 640855854 | L8: 48849432 | M8: 167301553 | N8: 133392316 | O8: 886107830 | P8: 133390421 | Q8: 256251484 | R8: 246.37361 | S8: XBRL 2024, comparativo
A9: AGUAS-A | B9: 1 | C9: Servicios básicos e infraestructura | D9: 2024 | E9: =IFERROR(INDEX(Empresas!$H$2:$H$23,MATCH($A9,Empresas!$B$2:$B$23,0))&"","") | F9: 288702263 | G9: 351513489 | H9: 3018159335 | I9: 1726043867 | J9: 1292115468 | K9: 663124854 | L9: 49334397 | M9: 158648372 | N9: 124341654 | O9: 1292066950 | P9: 124339646 | Q9: 250689914 | R9: 273.23779 | S9: XBRL 2025, comparativo
A10: AGUAS-A | B10: 1 | C10: Servicios básicos e infraestructura | D10: 2025 | E10: =IFERROR(INDEX(Empresas!$H$2:$H$23,MATCH($A10,Empresas!$B$2:$B$23,0))&"","") | F10: 349120706 | G10: 279876332 | H10: 3160940487 | I10: 1837956795 | J10: 1322983692 | K10: 712787064 | L10: 55425087 | M10: 177385719 | N10: 139810947 | O10: 1322935141 | P10: 139808491 | Q10: 270051183 | R10: 358.47021 | S10: XBRL 2025, actual
A11: COLBUN | B11: 1 | C11: Servicios básicos e infraestructura | D11: 2017 | E11: =IFERROR(INDEX(Empresas!$H$2:$H$23,MATCH($A11,Empresas!$B$2:$B$23,0))&"","") | F11: 1147162 | G11: 360397 | H11: 6922542 | I11: 2971835 | J11: 3950707 | K11: 1548412 | L11: 84954 | M11: 322682 | N11: 288602 | O11: 3724532 | P11: 270985 | Q11: 383837 | R11: 140.41795 | S11: XBRL 2018, comparativo
A12: COLBUN | B12: 1 | C12: Servicios básicos e infraestructura | D12: 2018 | E12: =IFERROR(INDEX(Empresas!$H$2:$H$23,MATCH($A12,Empresas!$B$2:$B$23,0))&"","") | F12: 1151263 | G12: 345365 | H12: 6778349 | I12: 2921411 | J12: 3856938 | K12: 1571347 | L12: 83871 | M12: 328843 | N12: 230425 | O12: 3656514 | P12: 240350 | Q12: 393600 | R12: 138.35886 | S12: XBRL 2018, actual
A13: COLBUN | B13: 1 | C13: Servicios básicos e infraestructura | D13: 2019 | E13: =IFERROR(INDEX(Empresas!$H$2:$H$23,MATCH($A13,Empresas!$B$2:$B$23,0))&"","") | F13: 1139451 | G13: 338298 | H13: 6705350 | I13: 2969715 | J13: 3735635 | K13: 1487387 | L13: 91069 | M13: 270182 | N13: 201966 | O13: 3536293 | P13: 203047 | Q13: 337210 | R13: 119.15425 | S13: XBRL 2020, comparativo
... A28: ENELAM | B28: 1 | C28: Servicios básicos e infraestructura | D28: 2025 | E28: =IFERROR(INDEX(Empresas!$H$2:$H$23,MATCH($A28,Empresas!$B$2:$B$23,0))&"","") | F28: 6695824 | G28: 7737034 | H28: 34871081 | I28: 16294367 | J28: 18576714 | K28: 12818885 | L28: 1307207 | M28: 1902104 | N28: 1345692 | O28: 16023472 | P28: 960070 | Q28: 3051640 | R28: 85.657028 | S28: XBRL 2025, actual
A29: ENELCHILE | B29: 1 | C29: Servicios básicos e infraestructura | D29: 2017 | E29: =IFERROR(INDEX(Empresas!$H$2:$H$23,MATCH($A29,Empresas!$B$2:$B$23,0))&"","") | F29: 1055136552 | G29: 816816646 | H29: 5694773008 | I29: 1907811351 | J29: 3786961657 | K29: 2484101582 | L29: 53510882 | M29: 666760212 | N29: 523417911 | O29: 2983384010 | Q29: 691871770 | R29: 47.22459 | S29: XBRL 2018, comparativo
A30: ENELCHILE | B30: 1 | C30: Servicios básicos e infraestructura | D30: 2018 | E30: =IFERROR(INDEX(Empresas!$H$2:$H$23,MATCH($A30,Empresas!$B$2:$B$23,0))&"","") | F30: 996947772 | G30: 1217464152 | H30: 7488020164 | I30: 3813856383 | J30: 3674163781 | K30: 2410360459 | L30: 122184189 | M30: 566330276 | N30: 412847757 | O30: 3421228519 | Q30: 674015100 | R30: 45.228989 | S30: XBRL 2018, actual
A31: ENELCHILE | B31: 1 | C31: Servicios básicos e infraestructura | D31: 2019 | E31: =IFERROR(INDEX(Empresas!$H$2:$H$23,MATCH($A31,Empresas!$B$2:$B$23,0))&"","") | F31: 1018212660 | G31: 1041299852 | H31: 7857988164 | I31: 4110704512 | J31: 3747283652 | K31: 2624576323 | L31: 164897900 | M31: 377321122 | N31: 316093218 | O31: 3484697986 | P31: 296153605 | Q31: 537895036 | R31: 49.978222 | S31: XBRL 2020, comparativo
A32: ENELCHILE | B32: 1 | C32: Servicios básicos e infraestructura | D32: 2020 | E32: =IFERROR(INDEX(Empresas!$H$2:$H$23,MATCH($A32,Empresas!$B$2:$B$23,0))&"","") | F32: 1026401196 | G32: 1045480165 | H32: 7904471584 | I32: 4310197085 | J32: 3594274499 | K32: 2548384317 | L32: 127408771 | M32: -133691942 | N32: -52386835 | O32: 3351915790 | P32: -50860313 | Q32: -9598853 | R32: 41.88335 | S32: XBRL 2020, actual
A33: ENELCHILE | B33: 1 | C33: Servicios básicos e infraestructura | D33: 2021 | E33: =IFERROR(INDEX(Empresas!$H$2:$H$23,MATCH($A33,Empresas!$B$2:$B$23,0))&"","") | F33: 1268252493 | G33: 2132326217 | H33: 9500323596 | I33: 6153830698 | J33: 3346492898 | K33: 2829682404 | L33: 174043116 | M33: 115848792 | N33: 100710134 | O33: 3097868353 | P33: 85153969 | Q33: 288496122 | R33: 24.271528 | S33: XBRL 2022, comparativo
A34: ENELCHILE | B34: 1 | C34: Servicios básicos e infraestructura | D34: 2022 | E34: =IFERROR(INDEX(Empresas!$H$2:$H$23,MATCH($A34,Empresas!$B$2:$B$23,0))&"","") | F34: 3064242319 | G34: 3168491880 | H34: 11865579732 | I34: 7476640429 | J34: 4388939303 | K34: 4379000090 | L34: 193618033 | M34: 1778680669 | N34: 1308983789 | O34: 4097200895 | P34: 1252082258 | Q34: 1916363887 | R34: 32.246185 | S34: XBRL 2022, actual
A35: ENELCHILE | B35: 1 | C35: Servicios básicos e infraestructura | D35: 2023 | E35: =IFERROR(INDEX(Empresas!$H$2:$H$23,MATCH($A35,Empresas!$B$2:$B$23,0))&"","") | F35: 2370971259 | G35: 2793918344 | H35: 11833721036 | I35: 7072834764 | J35: 4760886272 | K35: 4262591097 | L35: 247067556 | M35: 906925876 | N35: 680013391 | O35: 4446079918 | P35: 633455775 | Q35: 1000381600 | R35: 47.549023 | S35: XBRL 2024, comparativo
A36: ENELCHILE | B36: 1 | C36: Servicios básicos e infraestructura | D36: 2024 | E36: =IFERROR(INDEX(Empresas!$H$2:$H$23,MATCH($A36,Empresas!$B$2:$B$23,0))&"","") | F36: 2242156 | G36: 2251458 | H36: 12765086 | I36: 7419784 | J36: 5345302 | K36: 4137511 | L36: 246450 | M36: 239443 | N36: 202432 | O36: 4976415 | P36: 153763 | Q36: 414518 | R36: 52.085506 | S36: XBRL 2025, comparativo
A37: ENELCHILE | B37: 1 | C37: Servicios básicos e infraestructura | D37: 2025 | E37: =IFERROR(INDEX(Empresas!$H$2:$H$23,MATCH($A37,Empresas!$B$2:$B$23,0))&"","") | F37: 2239087 | G37: 2473336 | H37: 12903659 | I37: 7354152 | J37: 5549507 | K37: 4509547 | L37: 330272 | M37: 794958 | N37: 584899 | O37: 5175869 | P37: 537629 | Q37: 1055798 | R37: 71.38958 | S37: XBRL 2025, actual
A38: ECL | B38: 1 | C38: Servicios básicos e infraestructura | D38: 2017 | E38: =IFERROR(INDEX(Empresas!$H$2:$H$23,MATCH($A38,Empresas!$B$2:$B$23,0))&"","") | F38: 381378 | G38: 333019 | H38: 3364203 | I38: 1298732 | J38: 2065471 | K38: 1054062 | L38: 11594 | M38: 143494 | N38: 109010 | O38: 1991493 | P38: 100862 | Q38: 148439 | R38: 1321.5504 | S38: XBRL 2018, comparativo
A39: ECL | B39: 1 | C39: Servicios básicos e infraestructura | D39: 2018 | E39: =IFERROR(INDEX(Empresas!$H$2:$H$23,MATCH($A39,Empresas!$B$2:$B$23,0))&"","") | F39: 427615 | G39: 305766 | H39: 3462736 | I39: 1324712 | J39: 2138024 | K39: 1275296 | L39: 12771 | M39: 149562 | N39: 111223 | O39: 2069806 | P39: 102582 | Q39: 151834 | R39: 1268.027 | S39: XBRL 2018, actual
A40: ECL | B40: 1 | C40: Servicios básicos e infraestructura | D40: 2019 | E40: =IFERROR(INDEX(Empresas!$H$2:$H$23,MATCH($A40,Empresas!$B$2:$B$23,0))&"","") | F40: 485255 | G40: 357485 | H40: 3507790 | I40: 1384189 | J40: 2123601 | K40: 1454436 | L40: 37837 | M40: 161321 | N40: 118717 | O40: 2059251 | P40: 110823 | Q40: 189682 | R40: 1144.675 | S40: XBRL 2020, comparativo
A41: ECL | B41: 1 | C41: Servicios básicos e infraestructura | D41: 2020 | E41: =IFERROR(INDEX(Empresas!$H$2:$H$23,MATCH($A41,Empresas!$B$2:$B$23,0))&"","") | F41: 464866 | G41: 323459 | H41: 3720980 | I41: 1552972 | J41: 2168008 | K41: 1351658 | L41: 59476 | M41: 203722 | N41: 163531 | O41: 2168008 | P41: 163531 | Q41: 263554 | R41: 869.81396 | S41: XBRL 2020, actual
A42: ECL | B42: 1 | C42: Servicios básicos e infraestructura | D42: 2021 | E42: =IFERROR(INDEX(Empresas!$H$2:$H$23,MATCH($A42,Empresas!$B$2:$B$23,0))&"","") | F42: 616232 | G42: 397389 | H42: 3998862 | I42: 1826851 | J42: 2172011 | K42: 1478614 | L42: 88807 | M42: 60797 | N42: 47374 | O42: 2172011 | P42: 47374 | Q42: 127339 | R42: 501.96219 | S42: XBRL 2022, comparativo
... A48: ENTEL | B48: 1 | C48: Servicios básicos e infraestructura | D48: 2018 | E48: =IFERROR(INDEX(Empresas!$H$2:$H$23,MATCH($A48,Empresas!$B$2:$B$23,0))&"","") | F48: 810596112 | G48: 658742932 | H48: 3964215271 | I48: 2597793309 | J48: 1366421962 | K48: 1913174282 | L48: 77711185 | M48: -2270976 | N48: -23614092 | O48: 1366421962 | P48: -23614092 | Q48: 90913071 | R48: 2549.1682 | S48: XBRL 2018, actual
A49: ENTEL | B49: 1 | C49: Servicios básicos e infraestructura | D49: 2019 | E49: =IFERROR(INDEX(Empresas!$H$2:$H$23,MATCH($A49,Empresas!$B$2:$B$23,0))&"","") | F49: 1350183140 | G49: 891001450 | H49: 5169493602 | I49: 3560819204 | J49: 1608674398 | K49: 1978791988 | L49: 97558997 | M49: 240209837 | N49: 154152106 | O49: 1608674398 | Q49: 343916569 | R49: 2533.2522 | S49: XBRL 2020, comparativo
A50: ENTEL | B50: 1 | C50: Servicios básicos e infraestructura | D50: 2020 | E50: =IFERROR(INDEX(Empresas!$H$2:$H$23,MATCH($A50,Empresas!$B$2:$B$23,0))&"","") | F50: 1376958931 | G50: 814156775 | H50: 4888444532 | I50: 3379954105 | J50: 1508490427 | K50: 2092644232 | L50: 102535938 | M50: 93954056 | N50: 84466248 | O50: 1508490427 | Q50: 212469036 | R50: 2153.9814 | S50: XBRL 2020, actual
A51: ENTEL | B51: 1 | C51: Servicios básicos e infraestructura | D51: 2021 | E51: =IFERROR(INDEX(Empresas!$H$2:$H$23,MATCH($A51,Empresas!$B$2:$B$23,0))&"","") | F51: 1295049133 | G51: 1157171716 | H51: 5470958637 | I51: 3967913270 | J51: 1503045367 | K51: 2408809597 | L51: 113951133 | M51: 118630360 | N51: 74975311 | O51: 1503045367 | P51: 74975311 | Q51: 294374685 | R51: 1837.4656 | S51: XBRL 2022, comparativo
A52: ENTEL | B52: 1 | C52: Servicios básicos e infraestructura | D52: 2022 | E52: =IFERROR(INDEX(Empresas!$H$2:$H$23,MATCH($A52,Empresas!$B$2:$B$23,0))&"","") | F52: 1484646595 | G52: 1132020070 | H52: 5595346439 | I52: 4040830663 | J52: 1554515776 | K52: 2540682904 | L52: 113696383 | M52: 539751444 | N52: 456787332 | O52: 1554515776 | P52: 456787332 | Q52: 757608676 | R52: 2344.2937 | S52: XBRL 2022, actual
A53: ENTEL | B53: 1 | C53: Servicios básicos e infraestructura | D53: 2023 | E53: =IFERROR(INDEX(Empresas!$H$2:$H$23,MATCH($A53,Empresas!$B$2:$B$23,0))&"","") | F53: 1596064579 | G53: 1336992696 | H53: 5698687722 | I53: 4023234762 | J53: 1675452960 | K53: 2473692310 | L53: 113270200 | M53: 120594631 | N53: 88884366 | O53: 1675452960 | P53: 88884366 | Q53: 249569340 | R53: 2655.2822 | S53: XBRL 2024, comparativo
A54: ENTEL | B54: 1 | C54: Servicios básicos e infraestructura | D54: 2024 | E54: =IFERROR(INDEX(Empresas!$H$2:$H$23,MATCH($A54,Empresas!$B$2:$B$23,0))&"","") | F54: 1354153503 | G54: 1390644381 | H54: 5839398906 | I54: 4003379269 | J54: 1836019637 | K54: 2703236728 | L54: 111986497 | M54: 131167257 | N54: 67672129 | O54: 1836019637 | P54: 67672129 | Q54: 230852594 | R54: 2653.1975 | S54: XBRL 2025, comparativo
A55: ENTEL | B55: 1 | C55: Servicios básicos e infraestructura | D55: 2025 | E55: =IFERROR(INDEX(Empresas!$H$2:$H$23,MATCH($A55,Empresas!$B$2:$B$23,0))&"","") | F55: 1349902280 | G55: 1165931045 | H55: 5716879713 | I55: 3773582832 | J55: 1943296881 | K55: 2954930278 | L55: 165362521 | M55: 89153460 | N55: 191396469 | O55: 1943296881 | P55: 191396469 | Q55: 249853484 | R55: 4522.3081 | S55: XBRL 2025, actual
A56: CENCOSUD | B56: 2 | C56: Consumo | D56: 2017 | E56: =IFERROR(INDEX(Empresas!$H$2:$H$23,MATCH($A56,Empresas!$B$2:$B$23,0))&"","") | F56: 2616704742 | G56: 2695719238 | H56: 10024711422 | I56: 6015689973 | J56: 4009021449 | K56: 10456987206 | L56: 297173197 | M56: 638419975 | N56: 440135976 | O56: 4010150786 | P56: 439988718 | Q56: 825410527 | R56: 1181.6542 | S56: XBRL 2018, comparativo
A57: CENCOSUD | B57: 2 | C57: Consumo | D57: 2018 | E57: =IFERROR(INDEX(Empresas!$H$2:$H$23,MATCH($A57,Empresas!$B$2:$B$23,0))&"","") | F57: 2649598319 | G57: 2622878167 | H57: 10634698845 | I57: 6390656921 | J57: 4244041924 | K57: 9646001747 | L57: 237011354 | M57: 278346717 | N57: 190594477 | O57: 4245504837 | P57: 191285239 | Q57: 608906016 | R57: 840.58185 | S57: XBRL 2018, actual
A58: CENCOSUD | B58: 2 | C58: Consumo | D58: 2019 | E58: =IFERROR(INDEX(Empresas!$H$2:$H$23,MATCH($A58,Empresas!$B$2:$B$23,0))&"","") | F58: 3211830302 | G58: 2537199479 | H58: 12248307991 | I58: 7258386384 | J58: 4989921607 | K58: 9548213456 | L58: 282095846 | M58: 329464815 | N58: 154617183 | O58: 4442538398 | P58: 114109633 | Q58: 713608184 | R58: 667.63141 | S58: XBRL 2020, comparativo
A59: CENCOSUD | B59: 2 | C59: Consumo | D59: 2020 | E59: =IFERROR(INDEX(Empresas!$H$2:$H$23,MATCH($A59,Empresas!$B$2:$B$23,0))&"","") | F59: 2750870198 | G59: 2523502528 | H59: 10845080030 | I59: 6326579185 | J59: 4518500845 | K59: 9836117393 | L59: 264941294 | M59: 202558250 | N59: 64980678 | O59: 3957334556 | P59: 22930607 | Q59: 593715165 | R59: 879.85071 | S59: XBRL 2020, actual
A60: CENCOSUD | B60: 2 | C60: Consumo | D60: 2021 | E60: =IFERROR(INDEX(Empresas!$H$2:$H$23,MATCH($A60,Empresas!$B$2:$B$23,0))&"","") | F60: 3360396781 | G60: 3161774685 | H60: 11951507481 | I60: 7217249903 | J60: 4734257578 | K60: 11760071408 | L60: 143512497 | M60: 755829320 | N60: 495135760 | O60: 4176462336 | P60: 471910200 | Q60: 1035297383 | R60: 1186.4556 | S60: XBRL 2022, comparativo
A61: CENCOSUD | B61: 2 | C61: Consumo | D61: 2022 | E61: =IFERROR(INDEX(Empresas!$H$2:$H$23,MATCH($A61,Empresas!$B$2:$B$23,0))&"","") | F61: 3108157445 | G61: 3753381559 | H61: 13340199791 | I61: 9093982389 | J61: 4246217402 | K61: 14202097551 | L61: 233871142 | M61: 641933421 | N61: 404748150 | O61: 3670812256 | P61: 338929324 | Q61: 1122918890 | R61: 1270.4199 | S61: XBRL 2022, actual
A62: CENCOSUD | B62: 2 | C62: Consumo | D62: 2023 | E62: =IFERROR(INDEX(Empresas!$H$2:$H$23,MATCH($A62,Empresas!$B$2:$B$23,0))&"","") | F62: 2976277224 | G62: 3798928406 | H62: 13573122529 | I62: 9295494767 | J62: 4277627762 | K62: 14230641548 | L62: 311890685 | M62: 513384871 | N62: 292212589 | O62: 3670611817 | P62: 220279761 | Q62: 999026496 | R62: 1608.3352 | S62: XBRL 2024, comparativo
... A163: COPEC | B163: 3 | C163: Industria, recursos naturales e inmobiliario | D163: 2025 | E163: =IFERROR(INDEX(Empresas!$H$2:$H$23,MATCH($A163,Empresas!$B$2:$B$23,0))&"","") | F163: 9096891 | G163: 5223996 | H163: 33209748 | I163: 18290348 | J163: 14919400 | K163: 29637952 | L163: 629390 | M163: 1232298 | N163: 950179 | O163: 14318298 | P163: 876851 | Q163: 1454083 | R163: 6932.1284 | S163: XBRL 2025, actual

Sheet Captura_Fin
A1: nemotecnico | B1: cod_sector | C1: sector | D1: anio | E1: moneda | F1: activo_total | G1: pasivo_total | H1: patrimonio_total | I1: efectivo | J1: depositos | K1: colocaciones | L1: ingreso_operacional_neto | M1: gastos_operacionales | N1: gasto_provisiones | O1: ganancia_antes_impuestos | P1: ganancia_ejercicio | Q1: precio_ajustado_cierre | R1: fuente | S1: observaciones
A2: CHILE | B2: 4 | C2: Financiero (bancos) | D2: 2017 | E2: =IFERROR(INDEX(Empresas!$H$2:$H$23,MATCH($A2,Empresas!$B$2:$B$23,0))&"","") | F2: 32824188 | G2: 29718473 | H2: 3105715 | I2: 1057393 | J2: 18983484 | K2: 24881353 | L2: 1709270 | M2: -789298 | N2: -234982 | O2: 691047 | P2: 576013 | Q2: 60.088425 | R2: CMF, estados mensuales 12/2017, MM$
A3: CHILE | B3: 4 | C3: Financiero (bancos) | D3: 2018 | E3: =IFERROR(INDEX(Empresas!$H$2:$H$23,MATCH($A3,Empresas!$B$2:$B$23,0))&"","") | F3: 35926459 | G3: 32622306 | H3: 3304153 | I3: 880081 | J3: 20240662 | K3: 27307223 | L3: 1873283 | M3: -847724 | N3: -281410 | O3: 751404 | P3: 594873 | Q3: 65.215981 | R3: CMF, estados mensuales 12/2018, MM$
A4: CHILE | B4: 4 | C4: Financiero (bancos) | D4: 2019 | E4: =IFERROR(INDEX(Empresas!$H$2:$H$23,MATCH($A4,Empresas!$B$2:$B$23,0))&"","") | F4: 41273333 | G4: 37745110 | H4: 3528223 | I4: 2392166 | J4: 22182751 | K4: 29334052 | L4: 2014520 | M4: -911004 | N4: -347274 | O4: 762692 | P4: 593009 | Q4: 54.254173 | R4: CMF, estados mensuales 12/2019, MM$
A5: CHILE | B5: 4 | C5: Financiero (bancos) | D5: 2020 | E5: =IFERROR(INDEX(Empresas!$H$2:$H$23,MATCH($A5,Empresas!$B$2:$B$23,0))&"","") | F5: 46095131 | G5: 42368863 | H5: 3726268 | I5: 2560216 | J5: 24066770 | K5: 30190058 | L5: 1938743 | M5: -882331 | N5: -462680 | O5: 589071 | P5: 463109 | Q5: 51.982399 | R5: CMF, estados mensuales 12/2020, MM$
A6: CHILE | B6: 4 | C6: Financiero (bancos) | D6: 2021 | E6: =IFERROR(INDEX(Empresas!$H$2:$H$23,MATCH($A6,Empresas!$B$2:$B$23,0))&"","") | F6: 51702439 | G6: 47479425 | H6: 4223014 | I6: 3713734 | J6: 27682797 | K6: 33537758 | L6: 2230257 | M6: -887764 | N6: -373260 | O6: 971473 | P6: 792923 | Q6: 48.897358 | R6: CMF, estados mensuales 12/2021, MM$
A7: CHILE | B7: 4 | C7: Financiero (bancos) | D7: 2022 | E7: =IFERROR(INDEX(Empresas!$H$2:$H$23,MATCH($A7,Empresas!$B$2:$B$23,0))&"","") | F7: 55255362 | G7: 50397034 | H7: 4858327.9 | I7: 2764883.9 | J7: 27540373 | K7: 35916413 | L7: 3115792.3 | M7: -995483.41 | N7: -435117.02 | O7: 1685191.9 | P7: 1409435.3 | Q7: 68.847427 | R7: CMF, estados mensuales 12/2022, MM$
A8: CHILE | B8: 4 | C8: Financiero (bancos) | D8: 2023 | E8: =IFERROR(INDEX(Empresas!$H$2:$H$23,MATCH($A8,Empresas!$B$2:$B$23,0))&"","") | F8: 55792552 | G8: 50555267 | H8: 5237284.7 | I8: 2464647.7 | J8: 28687222 | K8: 36831736 | L8: 2997278.2 | M8: -1118503.9 | N8: -361252.1 | O8: 1517522.1 | P8: 1243634.8 | Q8: 90.303284 | R8: CMF, estados mensuales 12/2023, MM$
A9: CHILE | B9: 4 | C9: Financiero (bancos) | D9: 2024 | E9: =IFERROR(INDEX(Empresas!$H$2:$H$23,MATCH($A9,Empresas!$B$2:$B$23,0))&"","") | F9: 52095442 | G9: 46472440 | H9: 5623001.4 | I9: 2699076.1 | J9: 28432005 | K9: 38089036 | L9: 3050285.2 | M9: -1132734.1 | N9: -391753.97 | O9: 1525797.1 | P9: 1207391.7 | Q9: 98.645157 | R9: CMF, estados mensuales 12/2024, MM$
A10: CHILE | B10: 4 | C10: Financiero (bancos) | D10: 2025 | E10: =IFERROR(INDEX(Empresas!$H$2:$H$23,MATCH($A10,Empresas!$B$2:$B$23,0))&"","") | F10: 54100904 | G10: 48301368 | H10: 5799536.2 | I10: 2590986.3 | J10: 28470164 | K10: 38354999 | L10: 3026042.7 | M10: -1130937.5 | N10: -381922.56 | O10: 1513182.7 | P10: 1192261.6 | Q10: 164.06694 | R10: CMF, estados mensuales 12/2025, MM$
A11: BCI | B11: 4 | C11: Financiero (bancos) | D11: 2017 | E11: =IFERROR(INDEX(Empresas!$H$2:$H$23,MATCH($A11,Empresas!$B$2:$B$23,0))&"","") | F11: 33883396 | G11: 31155110 | H11: 2728286 | I11: 1495732 | J11: 20226470 | K11: 24130419 | L11: 1380702 | M11: -741612 | N11: -212653 | O11: 538979 | P11: 371425 | Q11: 20320.629 | R11: CMF, estados mensuales 12/2017, MM$
A12: BCI | B12: 4 | C12: Financiero (bancos) | D12: 2018 | E12: =IFERROR(INDEX(Empresas!$H$2:$H$23,MATCH($A12,Empresas!$B$2:$B$23,0))&"","") | F12: 41349717 | G12: 37891354 | H12: 3458363 | I12: 2058757 | J12: 24551315 | K12: 29543095 | L12: 1585203 | M12: -864277 | N12: -266313 | O12: 519649 | P12: 395847 | Q12: 22217.955 | R12: CMF, estados mensuales 12/2018, MM$
A13: BCI | B13: 4 | C13: Financiero (bancos) | D13: 2019 | E13: =IFERROR(INDEX(Empresas!$H$2:$H$23,MATCH($A13,Empresas!$B$2:$B$23,0))&"","") | F13: 50336620 | G13: 46544100 | H13: 3792520 | I13: 3153760 | J13: 27553455 | K13: 33212457 | L13: 1891788 | M13: -957731 | N13: -415519 | O13: 531176 | P13: 402739 | Q13: 17913.963 | R13: CMF, estados mensuales 12/2019, MM$
... A37: ITAUCL | B37: 4 | C37: Financiero (bancos) | D37: 2025 | E37: =IFERROR(INDEX(Empresas!$H$2:$H$23,MATCH($A37,Empresas!$B$2:$B$23,0))&"","") | F37: 43916278 | G37: 39607525 | H37: 4308752.7 | I37: 2892660.3 | J37: 21456814 | K37: 28119106 | L37: 1518133 | M37: -834788.8 | N37: -319328.39 | O37: 364015.81 | P37: 428108.53 | Q37: 18837.979 | R37: CMF, estados mensuales 12/2025, MM$

Sheet Ratios_NoFin
A1: nemotecnico | B1: cod_sector | C1: sector | D1: anio | E1: EBIT | F1: F1_liquidez | G1: F2_capital_trabajo | H1: F3_eficiencia | I1: F4_rentabilidad_ROA | J1: F5_endeudamiento | K1: F6_cobertura | L1: F7_uso_activos | M1: F8_mercado_retorno | N1: ROE_descriptivo | O1: familias_validas | P1: cuadre_contable
A2: =Captura_NoFin!A2 | B2: =Captura_NoFin!B2 | C2: =Captura_NoFin!C2 | D2: =Captura_NoFin!D2 | E2: =IF(COUNT(Captura_NoFin!M2,Captura_NoFin!L2)<2,"",Captura_NoFin!M2+ABS(Captura_NoFin!L2)) | F2: =IF(COUNT(Captura_NoFin!F2,Captura_NoFin!G2)<2,"",IFERROR(Captura_NoFin!F2/Captura_NoFin!G2,"")) | G2: =IF(COUNT(Captura_NoFin!F2,Captura_NoFin!G2,Captura_NoFin!H2)<3,"",IFERROR((Captura_NoFin!F2-Captura_NoFin!G2)/Captura_NoFin!H2,"")) | H2: =IF(OR(E2="",COUNT(Captura_NoFin!K2)<1),"",IFERROR(E2/Captura_NoFin!K2,"")) | I2: =IF(COUNT(Captura_NoFin!N2,Captura_NoFin!H2)<2,"",IFERROR(Captura_NoFin!N2/Captura_NoFin!H2,"")) | J2: =IF(COUNT(Captura_NoFin!I2,Captura_NoFin!H2)<2,"",IFERROR(Captura_NoFin!I2/Captura_NoFin!H2,"")) | K2: =IF(OR(E2="",COUNT(Captura_NoFin!L2)<1),"",IFERROR(E2/ABS(Captura_NoFin!L2),"")) | L2: =IF(COUNT(Captura_NoFin!K2,Captura_NoFin!H2)<2,"",IFERROR(Captura_NoFin!K2/Captura_NoFin!H2,"")) | M2: =IF(COUNT(Captura_NoFin!R2)<1,"",IFERROR(IF(D2=2017,Captura_NoFin!R2/INDEX(Empresas!$I$2:$I$23,MATCH($A2,Empresas!$B$2:$B$23,0))-1,IF(COUNT(Captura_NoFin!R1)<1,"",Captura_NoFin!R2/Captura_NoFin!R1-1)),"")) | N2: =IF(COUNT(Captura_NoFin!P2,Captura_NoFin!O2)<2,"",IF(Captura_NoFin!O2<=0,"",Captura_NoFin!P2/Captura_NoFin!O2)) | O2: =COUNT(F2:M2) | P2: =IF(COUNT(Captura_NoFin!H2,Captura_NoFin!I2,Captura_NoFin!J2)<3,"",IF(ABS(Captura_NoFin!H2-Captura_NoFin!I2-Captura_NoFin!J2)<=0.005*ABS(Captura_NoFin!H2),"OK","REVISAR"))
A3: =Captura_NoFin!A3 | B3: =Captura_NoFin!B3 | C3: =Captura_NoFin!C3 | D3: =Captura_NoFin!D3 | E3: =IF(COUNT(Captura_NoFin!M3,Captura_NoFin!L3)<2,"",Captura_NoFin!M3+ABS(Captura_NoFin!L3)) | F3: =IF(COUNT(Captura_NoFin!F3,Captura_NoFin!G3)<2,"",IFERROR(Captura_NoFin!F3/Captura_NoFin!G3,"")) | G3: =IF(COUNT(Captura_NoFin!F3,Captura_NoFin!G3,Captura_NoFin!H3)<3,"",IFERROR((Captura_NoFin!F3-Captura_NoFin!G3)/Captura_NoFin!H3,"")) | H3: =IF(OR(E3="",COUNT(Captura_NoFin!K3)<1),"",IFERROR(E3/Captura_NoFin!K3,"")) | I3: =IF(COUNT(Captura_NoFin!N3,Captura_NoFin!H3)<2,"",IFERROR(Captura_NoFin!N3/Captura_NoFin!H3,"")) | J3: =IF(COUNT(Captura_NoFin!I3,Captura_NoFin!H3)<2,"",IFERROR(Captura_NoFin!I3/Captura_NoFin!H3,"")) | K3: =IF(OR(E3="",COUNT(Captura_NoFin!L3)<1),"",IFERROR(E3/ABS(Captura_NoFin!L3),"")) | L3: =IF(COUNT(Captura_NoFin!K3,Captura_NoFin!H3)<2,"",IFERROR(Captura_NoFin!K3/Captura_NoFin!H3,"")) | M3: =IF(COUNT(Captura_NoFin!R3)<1,"",IFERROR(IF(D3=2017,Captura_NoFin!R3/INDEX(Empresas!$I$2:$I$23,MATCH($A3,Empresas!$B$2:$B$23,0))-1,IF(COUNT(Captura_NoFin!R2)<1,"",Captura_NoFin!R3/Captura_NoFin!R2-1)),"")) | N3: =IF(COUNT(Captura_NoFin!P3,Captura_NoFin!O3)<2,"",IF(Captura_NoFin!O3<=0,"",Captura_NoFin!P3/Captura_NoFin!O3)) | O3: =COUNT(F3:M3) | P3: =IF(COUNT(Captura_NoFin!H3,Captura_NoFin!I3,Captura_NoFin!J3)<3,"",IF(ABS(Captura_NoFin!H3-Captura_NoFin!I3-Captura_NoFin!J3)<=0.005*ABS(Captura_NoFin!H3),"OK","REVISAR"))
A4: =Captura_NoFin!A4 | B4: =Captura_NoFin!B4 | C4: =Captura_NoFin!C4 | D4: =Captura_NoFin!D4 | E4: =IF(COUNT(Captura_NoFin!M4,Captura_NoFin!L4)<2,"",Captura_NoFin!M4+ABS(Captura_NoFin!L4)) | F4: =IF(COUNT(Captura_NoFin!F4,Captura_NoFin!G4)<2,"",IFERROR(Captura_NoFin!F4/Captura_NoFin!G4,"")) | G4: =IF(COUNT(Captura_NoFin!F4,Captura_NoFin!G4,Captura_NoFin!H4)<3,"",IFERROR((Captura_NoFin!F4-Captura_NoFin!G4)/Captura_NoFin!H4,"")) | H4: =IF(OR(E4="",COUNT(Captura_NoFin!K4)<1),"",IFERROR(E4/Captura_NoFin!K4,"")) | I4: =IF(COUNT(Captura_NoFin!N4,Captura_NoFin!H4)<2,"",IFERROR(Captura_NoFin!N4/Captura_NoFin!H4,"")) | J4: =IF(COUNT(Captura_NoFin!I4,Captura_NoFin!H4)<2,"",IFERROR(Captura_NoFin!I4/Captura_NoFin!H4,"")) | K4: =IF(OR(E4="",COUNT(Captura_NoFin!L4)<1),"",IFERROR(E4/ABS(Captura_NoFin!L4),"")) | L4: =IF(COUNT(Captura_NoFin!K4,Captura_NoFin!H4)<2,"",IFERROR(Captura_NoFin!K4/Captura_NoFin!H4,"")) | M4: =IF(COUNT(Captura_NoFin!R4)<1,"",IFERROR(IF(D4=2017,Captura_NoFin!R4/INDEX(Empresas!$I$2:$I$23,MATCH($A4,Empresas!$B$2:$B$23,0))-1,IF(COUNT(Captura_NoFin!R3)<1,"",Captura_NoFin!R4/Captura_NoFin!R3-1)),"")) | N4: =IF(COUNT(Captura_NoFin!P4,Captura_NoFin!O4)<2,"",IF(Captura_NoFin!O4<=0,"",Captura_NoFin!P4/Captura_NoFin!O4)) | O4: =COUNT(F4:M4) | P4: =IF(COUNT(Captura_NoFin!H4,Captura_NoFin!I4,Captura_NoFin!J4)<3,"",IF(ABS(Captura_NoFin!H4-Captura_NoFin!I4-Captura_NoFin!J4)<=0.005*ABS(Captura_NoFin!H4),"OK","REVISAR"))
A5: =Captura_NoFin!A5 | B5: =Captura_NoFin!B5 | C5: =Captura_NoFin!C5 | D5: =Captura_NoFin!D5 | E5: =IF(COUNT(Captura_NoFin!M5,Captura_NoFin!L5)<2,"",Captura_NoFin!M5+ABS(Captura_NoFin!L5)) | F5: =IF(COUNT(Captura_NoFin!F5,Captura_NoFin!G5)<2,"",IFERROR(Captura_NoFin!F5/Captura_NoFin!G5,"")) | G5: =IF(COUNT(Captura_NoFin!F5,Captura_NoFin!G5,Captura_NoFin!H5)<3,"",IFERROR((Captura_NoFin!F5-Captura_NoFin!G5)/Captura_NoFin!H5,"")) | H5: =IF(OR(E5="",COUNT(Captura_NoFin!K5)<1),"",IFERROR(E5/Captura_NoFin!K5,"")) | I5: =IF(COUNT(Captura_NoFin!N5,Captura_NoFin!H5)<2,"",IFERROR(Captura_NoFin!N5/Captura_NoFin!H5,"")) | J5: =IF(COUNT(Captura_NoFin!I5,Captura_NoFin!H5)<2,"",IFERROR(Captura_NoFin!I5/Captura_NoFin!H5,"")) | K5: =IF(OR(E5="",COUNT(Captura_NoFin!L5)<1),"",IFERROR(E5/ABS(Captura_NoFin!L5),"")) | L5: =IF(COUNT(Captura_NoFin!K5,Captura_NoFin!H5)<2,"",IFERROR(Captura_NoFin!K5/Captura_NoFin!H5,"")) | M5: =IF(COUNT(Captura_NoFin!R5)<1,"",IFERROR(IF(D5=2017,Captura_NoFin!R5/INDEX(Empresas!$I$2:$I$23,MATCH($A5,Empresas!$B$2:$B$23,0))-1,IF(COUNT(Captura_NoFin!R4)<1,"",Captura_NoFin!R5/Captura_NoFin!R4-1)),"")) | N5: =IF(COUNT(Captura_NoFin!P5,Captura_NoFin!O5)<2,"",IF(Captura_NoFin!O5<=0,"",Captura_NoFin!P5/Captura_NoFin!O5)) | O5: =COUNT(F5:M5) | P5: =IF(COUNT(Captura_NoFin!H5,Captura_NoFin!I5,Captura_NoFin!J5)<3,"",IF(ABS(Captura_NoFin!H5-Captura_NoFin!I5-Captura_NoFin!J5)<=0.005*ABS(Captura_NoFin!H5),"OK","REVISAR"))
A6: =Captura_NoFin!A6 | B6: =Captura_NoFin!B6 | C6: =Captura_NoFin!C6 | D6: =Captura_NoFin!D6 | E6: =IF(COUNT(Captura_NoFin!M6,Captura_NoFin!L6)<2,"",Captura_NoFin!M6+ABS(Captura_NoFin!L6)) | F6: =IF(COUNT(Captura_NoFin!F6,Captura_NoFin!G6)<2,"",IFERROR(Captura_NoFin!F6/Captura_NoFin!G6,"")) | G6: =IF(COUNT(Captura_NoFin!F6,Captura_NoFin!G6,Captura_NoFin!H6)<3,"",IFERROR((Captura_NoFin!F6-Captura_NoFin!G6)/Captura_NoFin!H6,"")) | H6: =IF(OR(E6="",COUNT(Captura_NoFin!K6)<1),"",IFERROR(E6/Captura_NoFin!K6,"")) | I6: =IF(COUNT(Captura_NoFin!N6,Captura_NoFin!H6)<2,"",IFERROR(Captura_NoFin!N6/Captura_NoFin!H6,"")) | J6: =IF(COUNT(Captura_NoFin!I6,Captura_NoFin!H6)<2,"",IFERROR(Captura_NoFin!I6/Captura_NoFin!H6,"")) | K6: =IF(OR(E6="",COUNT(Captura_NoFin!L6)<1),"",IFERROR(E6/ABS(Captura_NoFin!L6),"")) | L6: =IF(COUNT(Captura_NoFin!K6,Captura_NoFin!H6)<2,"",IFERROR(Captura_NoFin!K6/Captura_NoFin!H6,"")) | M6: =IF(COUNT(Captura_NoFin!R6)<1,"",IFERROR(IF(D6=2017,Captura_NoFin!R6/INDEX(Empresas!$I$2:$I$23,MATCH($A6,Empresas!$B$2:$B$23,0))-1,IF(COUNT(Captura_NoFin!R5)<1,"",Captura_NoFin!R6/Captura_NoFin!R5-1)),"")) | N6: =IF(COUNT(Captura_NoFin!P6,Captura_NoFin!O6)<2,"",IF(Captura_NoFin!O6<=0,"",Captura_NoFin!P6/Captura_NoFin!O6)) | O6: =COUNT(F6:M6) | P6: =IF(COUNT(Captura_NoFin!H6,Captura_NoFin!I6,Captura_NoFin!J6)<3,"",IF(ABS(Captura_NoFin!H6-Captura_NoFin!I6-Captura_NoFin!J6)<=0.005*ABS(Captura_NoFin!H6),"OK","REVISAR"))
A7: =Captura_NoFin!A7 | B7: =Captura_NoFin!B7 | C7: =Captura_NoFin!C7 | D7: =Captura_NoFin!D7 | E7: =IF(COUNT(Captura_NoFin!M7,Captura_NoFin!L7)<2,"",Captura_NoFin!M7+ABS(Captura_NoFin!L7)) | F7: =IF(COUNT(Captura_NoFin!F7,Captura_NoFin!G7)<2,"",IFERROR(Captura_NoFin!F7/Captura_NoFin!G7,"")) | G7: =IF(COUNT(Captura_NoFin!F7,Captura_NoFin!G7,Captura_NoFin!H7)<3,"",IFERROR((Captura_NoFin!F7-Captura_NoFin!G7)/Captura_NoFin!H7,"")) | H7: =IF(OR(E7="",COUNT(Captura_NoFin!K7)<1),"",IFERROR(E7/Captura_NoFin!K7,"")) | I7: =IF(COUNT(Captura_NoFin!N7,Captura_NoFin!H7)<2,"",IFERROR(Captura_NoFin!N7/Captura_NoFin!H7,"")) | J7: =IF(COUNT(Captura_NoFin!I7,Captura_NoFin!H7)<2,"",IFERROR(Captura_NoFin!I7/Captura_NoFin!H7,"")) | K7: =IF(OR(E7="",COUNT(Captura_NoFin!L7)<1),"",IFERROR(E7/ABS(Captura_NoFin!L7),"")) | L7: =IF(COUNT(Captura_NoFin!K7,Captura_NoFin!H7)<2,"",IFERROR(Captura_NoFin!K7/Captura_NoFin!H7,"")) | M7: =IF(COUNT(Captura_NoFin!R7)<1,"",IFERROR(IF(D7=2017,Captura_NoFin!R7/INDEX(Empresas!$I$2:$I$23,MATCH($A7,Empresas!$B$2:$B$23,0))-1,IF(COUNT(Captura_NoFin!R6)<1,"",Captura_NoFin!R7/Captura_NoFin!R6-1)),"")) | N7: =IF(COUNT(Captura_NoFin!P7,Captura_NoFin!O7)<2,"",IF(Captura_NoFin!O7<=0,"",Captura_NoFin!P7/Captura_NoFin!O7)) | O7: =COUNT(F7:M7) | P7: =IF(COUNT(Captura_NoFin!H7,Captura_NoFin!I7,Captura_NoFin!J7)<3,"",IF(ABS(Captura_NoFin!H7-Captura_NoFin!I7-Captura_NoFin!J7)<=0.005*ABS(Captura_NoFin!H7),"OK","REVISAR"))
A8: =Captura_NoFin!A8 | B8: =Captura_NoFin!B8 | C8: =Captura_NoFin!C8 | D8: =Captura_NoFin!D8 | E8: =IF(COUNT(Captura_NoFin!M8,Captura_NoFin!L8)<2,"",Captura_NoFin!M8+ABS(Captura_NoFin!L8)) | F8: =IF(COUNT(Captura_NoFin!F8,Captura_NoFin!G8)<2,"",IFERROR(Captura_NoFin!F8/Captura_NoFin!G8,"")) | G8: =IF(COUNT(Captura_NoFin!F8,Captura_NoFin!G8,Captura_NoFin!H8)<3,"",IFERROR((Captura_NoFin!F8-Captura_NoFin!G8)/Captura_NoFin!H8,"")) | H8: =IF(OR(E8="",COUNT(Captura_NoFin!K8)<1),"",IFERROR(E8/Captura_NoFin!K8,"")) | I8: =IF(COUNT(Captura_NoFin!N8,Captura_NoFin!H8)<2,"",IFERROR(Captura_NoFin!N8/Captura_NoFin!H8,"")) | J8: =IF(COUNT(Captura_NoFin!I8,Captura_NoFin!H8)<2,"",IFERROR(Captura_NoFin!I8/Captura_NoFin!H8,"")) | K8: =IF(OR(E8="",COUNT(Captura_NoFin!L8)<1),"",IFERROR(E8/ABS(Captura_NoFin!L8),"")) | L8: =IF(COUNT(Captura_NoFin!K8,Captura_NoFin!H8)<2,"",IFERROR(Captura_NoFin!K8/Captura_NoFin!H8,"")) | M8: =IF(COUNT(Captura_NoFin!R8)<1,"",IFERROR(IF(D8=2017,Captura_NoFin!R8/INDEX(Empresas!$I$2:$I$23,MATCH($A8,Empresas!$B$2:$B$23,0))-1,IF(COUNT(Captura_NoFin!R7)<1,"",Captura_NoFin!R8/Captura_NoFin!R7-1)),"")) | N8: =IF(COUNT(Captura_NoFin!P8,Captura_NoFin!O8)<2,"",IF(Captura_NoFin!O8<=0,"",Captura_NoFin!P8/Captura_NoFin!O8)) | O8: =COUNT(F8:M8) | P8: =IF(COUNT(Captura_NoFin!H8,Captura_NoFin!I8,Captura_NoFin!J8)<3,"",IF(ABS(Captura_NoFin!H8-Captura_NoFin!I8-Captura_NoFin!J8)<=0.005*ABS(Captura_NoFin!H8),"OK","REVISAR"))
A9: =Captura_NoFin!A9 | B9: =Captura_NoFin!B9 | C9: =Captura_NoFin!C9 | D9: =Captura_NoFin!D9 | E9: =IF(COUNT(Captura_NoFin!M9,Captura_NoFin!L9)<2,"",Captura_NoFin!M9+ABS(Captura_NoFin!L9)) | F9: =IF(COUNT(Captura_NoFin!F9,Captura_NoFin!G9)<2,"",IFERROR(Captura_NoFin!F9/Captura_NoFin!G9,"")) | G9: =IF(COUNT(Captura_NoFin!F9,Captura_NoFin!G9,Captura_NoFin!H9)<3,"",IFERROR((Captura_NoFin!F9-Captura_NoFin!G9)/Captura_NoFin!H9,"")) | H9: =IF(OR(E9="",COUNT(Captura_NoFin!K9)<1),"",IFERROR(E9/Captura_NoFin!K9,"")) | I9: =IF(COUNT(Captura_NoFin!N9,Captura_NoFin!H9)<2,"",IFERROR(Captura_NoFin!N9/Captura_NoFin!H9,"")) | J9: =IF(COUNT(Captura_NoFin!I9,Captura_NoFin!H9)<2,"",IFERROR(Captura_NoFin!I9/Captura_NoFin!H9,"")) | K9: =IF(OR(E9="",COUNT(Captura_NoFin!L9)<1),"",IFERROR(E9/ABS(Captura_NoFin!L9),"")) | L9: =IF(COUNT(Captura_NoFin!K9,Captura_NoFin!H9)<2,"",IFERROR(Captura_NoFin!K9/Captura_NoFin!H9,"")) | M9: =IF(COUNT(Captura_NoFin!R9)<1,"",IFERROR(IF(D9=2017,Captura_NoFin!R9/INDEX(Empresas!$I$2:$I$23,MATCH($A9,Empresas!$B$2:$B$23,0))-1,IF(COUNT(Captura_NoFin!R8)<1,"",Captura_NoFin!R9/Captura_NoFin!R8-1)),"")) | N9: =IF(COUNT(Captura_NoFin!P9,Captura_NoFin!O9)<2,"",IF(Captura_NoFin!O9<=0,"",Captura_NoFin!P9/Captura_NoFin!O9)) | O9: =COUNT(F9:M9) | P9: =IF(COUNT(Captura_NoFin!H9,Captura_NoFin!I9,Captura_NoFin!J9)<3,"",IF(ABS(Captura_NoFin!H9-Captura_NoFin!I9-Captura_NoFin!J9)<=0.005*ABS(Captura_NoFin!H9),"OK","REVISAR"))
A10: =Captura_NoFin!A10 | B10: =Captura_NoFin!B10 | C10: =Captura_NoFin!C10 | D10: =Captura_NoFin!D10 | E10: =IF(COUNT(Captura_NoFin!M10,Captura_NoFin!L10)<2,"",Captura_NoFin!M10+ABS(Captura_NoFin!L10)) | F10: =IF(COUNT(Captura_NoFin!F10,Captura_NoFin!G10)<2,"",IFERROR(Captura_NoFin!F10/Captura_NoFin!G10,"")) | G10: =IF(COUNT(Captura_NoFin!F10,Captura_NoFin!G10,Captura_NoFin!H10)<3,"",IFERROR((Captura_NoFin!F10-Captura_NoFin!G10)/Captura_NoFin!H10,"")) | H10: =IF(OR(E10="",COUNT(Captura_NoFin!K10)<1),"",IFERROR(E10/Captura_NoFin!K10,"")) | I10: =IF(COUNT(Captura_NoFin!N10,Captura_NoFin!H10)<2,"",IFERROR(Captura_NoFin!N10/Captura_NoFin!H10,"")) | J10: =IF(COUNT(Captura_NoFin!I10,Captura_NoFin!H10)<2,"",IFERROR(Captura_NoFin!I10/Captura_NoFin!H10,"")) | K10: =IF(OR(E10="",COUNT(Captura_NoFin!L10)<1),"",IFERROR(E10/ABS(Captura_NoFin!L10),"")) | L10: =IF(COUNT(Captura_NoFin!K10,Captura_NoFin!H10)<2,"",IFERROR(Captura_NoFin!K10/Captura_NoFin!H10,"")) | M10: =IF(COUNT(Captura_NoFin!R10)<1,"",IFERROR(IF(D10=2017,Captura_NoFin!R10/INDEX(Empresas!$I$2:$I$23,MATCH($A10,Empresas!$B$2:$B$23,0))-1,IF(COUNT(Captura_NoFin!R9)<1,"",Captura_NoFin!R10/Captura_NoFin!R9-1)),"")) | N10: =IF(COUNT(Captura_NoFin!P10,Captura_NoFin!O10)<2,"",IF(Captura_NoFin!O10<=0,"",Captura_NoFin!P10/Captura_NoFin!O10)) | O10: =COUNT(F10:M10) | P10: =IF(COUNT(Captura_NoFin!H10,Captura_NoFin!I10,Captura_NoFin!J10)<3,"",IF(ABS(Captura_NoFin!H10-Captura_NoFin!I10-Captura_NoFin!J10)<=0.005*ABS(Captura_NoFin!H10),"OK","REVISAR"))
A11: =Captura_NoFin!A11 | B11: =Captura_NoFin!B11 | C11: =Captura_NoFin!C11 | D11: =Captura_NoFin!D11 | E11: =IF(COUNT(Captura_NoFin!M11,Captura_NoFin!L11)<2,"",Captura_NoFin!M11+ABS(Captura_NoFin!L11)) | F11: =IF(COUNT(Captura_NoFin!F11,Captura_NoFin!G11)<2,"",IFERROR(Captura_NoFin!F11/Captura_NoFin!G11,"")) | G11: =IF(COUNT(Captura_NoFin!F11,Captura_NoFin!G11,Captura_NoFin!H11)<3,"",IFERROR((Captura_NoFin!F11-Captura_NoFin!G11)/Captura_NoFin!H11,"")) | H11: =IF(OR(E11="",COUNT(Captura_NoFin!K11)<1),"",IFERROR(E11/Captura_NoFin!K11,"")) | I11: =IF(COUNT(Captura_NoFin!N11,Captura_NoFin!H11)<2,"",IFERROR(Captura_NoFin!N11/Captura_NoFin!H11,"")) | J11: =IF(COUNT(Captura_NoFin!I11,Captura_NoFin!H11)<2,"",IFERROR(Captura_NoFin!I11/Captura_NoFin!H11,"")) | K11: =IF(OR(E11="",COUNT(Captura_NoFin!L11)<1),"",IFERROR(E11/ABS(Captura_NoFin!L11),"")) | L11: =IF(COUNT(Captura_NoFin!K11,Captura_NoFin!H11)<2,"",IFERROR(Captura_NoFin!K11/Captura_NoFin!H11,"")) | M11: =IF(COUNT(Captura_NoFin!R11)<1,"",IFERROR(IF(D11=2017,Captura_NoFin!R11/INDEX(Empresas!$I$2:$I$23,MATCH($A11,Empresas!$B$2:$B$23,0))-1,IF(COUNT(Captura_NoFin!R10)<1,"",Captura_NoFin!R11/Captura_NoFin!R10-1)),"")) | N11: =IF(COUNT(Captura_NoFin!P11,Captura_NoFin!O11)<2,"",IF(Captura_NoFin!O11<=0,"",Captura_NoFin!P11/Captura_NoFin!O11)) | O11: =COUNT(F11:M11) | P11: =IF(COUNT(Captura_NoFin!H11,Captura_NoFin!I11,Captura_NoFin!J11)<3,"",IF(ABS(Captura_NoFin!H11-Captura_NoFin!I11-Captura_NoFin!J11)<=0.005*ABS(Captura_NoFin!H11),"OK","REVISAR"))
A12: =Captura_NoFin!A12 | B12: =Captura_NoFin!B12 | C12: =Captura_NoFin!C12 | D12: =Captura_NoFin!D12 | E12: =IF(COUNT(Captura_NoFin!M12,Captura_NoFin!L12)<2,"",Captura_NoFin!M12+ABS(Captura_NoFin!L12)) | F12: =IF(COUNT(Captura_NoFin!F12,Captura_NoFin!G12)<2,"",IFERROR(Captura_NoFin!F12/Captura_NoFin!G12,"")) | G12: =IF(COUNT(Captura_NoFin!F12,Captura_NoFin!G12,Captura_NoFin!H12)<3,"",IFERROR((Captura_NoFin!F12-Captura_NoFin!G12)/Captura_NoFin!H12,"")) | H12: =IF(OR(E12="",COUNT(Captura_NoFin!K12)<1),"",IFERROR(E12/Captura_NoFin!K12,"")) | I12: =IF(COUNT(Captura_NoFin!N12,Captura_NoFin!H12)<2,"",IFERROR(Captura_NoFin!N12/Captura_NoFin!H12,"")) | J12: =IF(COUNT(Captura_NoFin!I12,Captura_NoFin!H12)<2,"",IFERROR(Captura_NoFin!I12/Captura_NoFin!H12,"")) | K12: =IF(OR(E12="",COUNT(Captura_NoFin!L12)<1),"",IFERROR(E12/ABS(Captura_NoFin!L12),"")) | L12: =IF(COUNT(Captura_NoFin!K12,Captura_NoFin!H12)<2,"",IFERROR(Captura_NoFin!K12/Captura_NoFin!H12,"")) | M12: =IF(COUNT(Captura_NoFin!R12)<1,"",IFERROR(IF(D12=2017,Captura_NoFin!R12/INDEX(Empresas!$I$2:$I$23,MATCH($A12,Empresas!$B$2:$B$23,0))-1,IF(COUNT(Captura_NoFin!R11)<1,"",Captura_NoFin!R12/Captura_NoFin!R11-1)),"")) | N12: =IF(COUNT(Captura_NoFin!P12,Captura_NoFin!O12)<2,"",IF(Captura_NoFin!O12<=0,"",Captura_NoFin!P12/Captura_NoFin!O12)) | O12: =COUNT(F12:M12) | P12: =IF(COUNT(Captura_NoFin!H12,Captura_NoFin!I12,Captura_NoFin!J12)<3,"",IF(ABS(Captura_NoFin!H12-Captura_NoFin!I12-Captura_NoFin!J12)<=0.005*ABS(Captura_NoFin!H12),"OK","REVISAR"))
A13: =Captura_NoFin!A13 | B13: =Captura_NoFin!B13 | C13: =Captura_NoFin!C13 | D13: =Captura_NoFin!D13 | E13: =IF(COUNT(Captura_NoFin!M13,Captura_NoFin!L13)<2,"",Captura_NoFin!M13+ABS(Captura_NoFin!L13)) | F13: =IF(COUNT(Captura_NoFin!F13,Captura_NoFin!G13)<2,"",IFERROR(Captura_NoFin!F13/Captura_NoFin!G13,"")) | G13: =IF(COUNT(Captura_NoFin!F13,Captura_NoFin!G13,Captura_NoFin!H13)<3,"",IFERROR((Captura_NoFin!F13-Captura_NoFin!G13)/Captura_NoFin!H13,"")) | H13: =IF(OR(E13="",COUNT(Captura_NoFin!K13)<1),"",IFERROR(E13/Captura_NoFin!K13,"")) | I13: =IF(COUNT(Captura_NoFin!N13,Captura_NoFin!H13)<2,"",IFERROR(Captura_NoFin!N13/Captura_NoFin!H13,"")) | J13: =IF(COUNT(Captura_NoFin!I13,Captura_NoFin!H13)<2,"",IFERROR(Captura_NoFin!I13/Captura_NoFin!H13,"")) | K13: =IF(OR(E13="",COUNT(Captura_NoFin!L13)<1),"",IFERROR(E13/ABS(Captura_NoFin!L13),"")) | L13: =IF(COUNT(Captura_NoFin!K13,Captura_NoFin!H13)<2,"",IFERROR(Captura_NoFin!K13/Captura_NoFin!H13,"")) | M13: =IF(COUNT(Captura_NoFin!R13)<1,"",IFERROR(IF(D13=2017,Captura_NoFin!R13/INDEX(Empresas!$I$2:$I$23,MATCH($A13,Empresas!$B$2:$B$23,0))-1,IF(COUNT(Captura_NoFin!R12)<1,"",Captura_NoFin!R13/Captura_NoFin!R12-1)),"")) | N13: =IF(COUNT(Captura_NoFin!P13,Captura_NoFin!O13)<2,"",IF(Captura_NoFin!O13<=0,"",Captura_NoFin!P13/Captura_NoFin!O13)) | O13: =COUNT(F13:M13) | P13: =IF(COUNT(Captura_NoFin!H13,Captura_NoFin!I13,Captura_NoFin!J13)<3,"",IF(ABS(Captura_NoFin!H13-Captura_NoFin!I13-Captura_NoFin!J13)<=0.005*ABS(Captura_NoFin!H13),"OK","REVISAR"))
... A163: =Captura_NoFin!A163 | B163: =Captura_NoFin!B163 | C163: =Captura_NoFin!C163 | D163: =Captura_NoFin!D163 | E163: =IF(COUNT(Captura_NoFin!M163,Captura_NoFin!L163)<2,"",Captura_NoFin!M163+ABS(Captura_NoFin!L163)) | F163: =IF(COUNT(Captura_NoFin!F163,Captura_NoFin!G163)<2,"",IFERROR(Captura_NoFin!F163/Captura_NoFin!G163,"")) | G163: =IF(COUNT(Captura_NoFin!F163,Captura_NoFin!G163,Captura_NoFin!H163)<3,"",IFERROR((Captura_NoFin!F163-Captura_NoFin!G163)/Captura_NoFin!H163,"")) | H163: =IF(OR(E163="",COUNT(Captura_NoFin!K163)<1),"",IFERROR(E163/Captura_NoFin!K163,"")) | I163: =IF(COUNT(Captura_NoFin!N163,Captura_NoFin!H163)<2,"",IFERROR(Captura_NoFin!N163/Captura_NoFin!H163,"")) | J163: =IF(COUNT(Captura_NoFin!I163,Captura_NoFin!H163)<2,"",IFERROR(Captura_NoFin!I163/Captura_NoFin!H163,"")) | K163: =IF(OR(E163="",COUNT(Captura_NoFin!L163)<1),"",IFERROR(E163/ABS(Captura_NoFin!L163),"")) | L163: =IF(COUNT(Captura_NoFin!K163,Captura_NoFin!H163)<2,"",IFERROR(Captura_NoFin!K163/Captura_NoFin!H163,"")) | M163: =IF(COUNT(Captura_NoFin!R163)<1,"",IFERROR(IF(D163=2017,Captura_NoFin!R163/INDEX(Empresas!$I$2:$I$23,MATCH($A163,Empresas!$B$2:$B$23,0))-1,IF(COUNT(Captura_NoFin!R162)<1,"",Captura_NoFin!R163/Captura_NoFin!R162-1)),"")) | N163: =IF(COUNT(Captura_NoFin!P163,Captura_NoFin!O163)<2,"",IF(Captura_NoFin!O163<=0,"",Captura_NoFin!P163/Captura_NoFin!O163)) | O163: =COUNT(F163:M163) | P163: =IF(COUNT(Captura_NoFin!H163,Captura_NoFin!I163,Captura_NoFin!J163)<3,"",IF(ABS(Captura_NoFin!H163-Captura_NoFin!I163-Captura_NoFin!J163)<=0.005*ABS(Captura_NoFin!H163),"OK","REVISAR"))

Sheet Ratios_Fin
A1: nemotecnico | B1: cod_sector | C1: sector | D1: anio | E1: F1_liquidez | F1: F3_eficiencia | G1: F4_rentabilidad_ROA | H1: F5_endeudamiento | I1: F6_cobertura | J1: F7_uso_activos | K1: F8_mercado_retorno | L1: ROE_descriptivo | M1: familias_validas | N1: cuadre_contable
A2: =Captura_Fin!A2 | B2: =Captura_Fin!B2 | C2: =Captura_Fin!C2 | D2: =Captura_Fin!D2 | E2: =IF(COUNT(Captura_Fin!I2,Captura_Fin!J2)<2,"",IFERROR(Captura_Fin!I2/Captura_Fin!J2,"")) | F2: =IF(COUNT(Captura_Fin!M2,Captura_Fin!L2)<2,"",IFERROR(ABS(Captura_Fin!M2)/Captura_Fin!L2,"")) | G2: =IF(COUNT(Captura_Fin!P2,Captura_Fin!F2)<2,"",IFERROR(Captura_Fin!P2/Captura_Fin!F2,"")) | H2: =IF(COUNT(Captura_Fin!G2,Captura_Fin!F2)<2,"",IFERROR(Captura_Fin!G2/Captura_Fin!F2,"")) | I2: =IF(COUNT(Captura_Fin!O2,Captura_Fin!N2)<2,"",IFERROR((Captura_Fin!O2+ABS(Captura_Fin!N2))/ABS(Captura_Fin!N2),"")) | J2: =IF(COUNT(Captura_Fin!L2,Captura_Fin!F2)<2,"",IFERROR(Captura_Fin!L2/Captura_Fin!F2,"")) | K2: =IF(COUNT(Captura_Fin!Q2)<1,"",IFERROR(IF(D2=2017,Captura_Fin!Q2/INDEX(Empresas!$I$2:$I$23,MATCH($A2,Empresas!$B$2:$B$23,0))-1,IF(COUNT(Captura_Fin!Q1)<1,"",Captura_Fin!Q2/Captura_Fin!Q1-1)),"")) | L2: =IF(COUNT(Captura_Fin!P2,Captura_Fin!H2)<2,"",IF(Captura_Fin!H2<=0,"",Captura_Fin!P2/Captura_Fin!H2)) | M2: =COUNT(E2:K2) | N2: =IF(COUNT(Captura_Fin!F2,Captura_Fin!G2,Captura_Fin!H2)<3,"",IF(ABS(Captura_Fin!F2-Captura_Fin!G2-Captura_Fin!H2)<=0.005*ABS(Captura_Fin!F2),"OK","REVISAR"))
A3: =Captura_Fin!A3 | B3: =Captura_Fin!B3 | C3: =Captura_Fin!C3 | D3: =Captura_Fin!D3 | E3: =IF(COUNT(Captura_Fin!I3,Captura_Fin!J3)<2,"",IFERROR(Captura_Fin!I3/Captura_Fin!J3,"")) | F3: =IF(COUNT(Captura_Fin!M3,Captura_Fin!L3)<2,"",IFERROR(ABS(Captura_Fin!M3)/Captura_Fin!L3,"")) | G3: =IF(COUNT(Captura_Fin!P3,Captura_Fin!F3)<2,"",IFERROR(Captura_Fin!P3/Captura_Fin!F3,"")) | H3: =IF(COUNT(Captura_Fin!G3,Captura_Fin!F3)<2,"",IFERROR(Captura_Fin!G3/Captura_Fin!F3,"")) | I3: =IF(COUNT(Captura_Fin!O3,Captura_Fin!N3)<2,"",IFERROR((Captura_Fin!O3+ABS(Captura_Fin!N3))/ABS(Captura_Fin!N3),"")) | J3: =IF(COUNT(Captura_Fin!L3,Captura_Fin!F3)<2,"",IFERROR(Captura_Fin!L3/Captura_Fin!F3,"")) | K3: =IF(COUNT(Captura_Fin!Q3)<1,"",IFERROR(IF(D3=2017,Captura_Fin!Q3/INDEX(Empresas!$I$2:$I$23,MATCH($A3,Empresas!$B$2:$B$23,0))-1,IF(COUNT(Captura_Fin!Q2)<1,"",Captura_Fin!Q3/Captura_Fin!Q2-1)),"")) | L3: =IF(COUNT(Captura_Fin!P3,Captura_Fin!H3)<2,"",IF(Captura_Fin!H3<=0,"",Captura_Fin!P3/Captura_Fin!H3)) | M3: =COUNT(E3:K3) | N3: =IF(COUNT(Captura_Fin!F3,Captura_Fin!G3,Captura_Fin!H3)<3,"",IF(ABS(Captura_Fin!F3-Captura_Fin!G3-Captura_Fin!H3)<=0.005*ABS(Captura_Fin!F3),"OK","REVISAR"))
A4: =Captura_Fin!A4 | B4: =Captura_Fin!B4 | C4: =Captura_Fin!C4 | D4: =Captura_Fin!D4 | E4: =IF(COUNT(Captura_Fin!I4,Captura_Fin!J4)<2,"",IFERROR(Captura_Fin!I4/Captura_Fin!J4,"")) | F4: =IF(COUNT(Captura_Fin!M4,Captura_Fin!L4)<2,"",IFERROR(ABS(Captura_Fin!M4)/Captura_Fin!L4,"")) | G4: =IF(COUNT(Captura_Fin!P4,Captura_Fin!F4)<2,"",IFERROR(Captura_Fin!P4/Captura_Fin!F4,"")) | H4: =IF(COUNT(Captura_Fin!G4,Captura_Fin!F4)<2,"",IFERROR(Captura_Fin!G4/Captura_Fin!F4,"")) | I4: =IF(COUNT(Captura_Fin!O4,Captura_Fin!N4)<2,"",IFERROR((Captura_Fin!O4+ABS(Captura_Fin!N4))/ABS(Captura_Fin!N4),"")) | J4: =IF(COUNT(Captura_Fin!L4,Captura_Fin!F4)<2,"",IFERROR(Captura_Fin!L4/Captura_Fin!F4,"")) | K4: =IF(COUNT(Captura_Fin!Q4)<1,"",IFERROR(IF(D4=2017,Captura_Fin!Q4/INDEX(Empresas!$I$2:$I$23,MATCH($A4,Empresas!$B$2:$B$23,0))-1,IF(COUNT(Captura_Fin!Q3)<1,"",Captura_Fin!Q4/Captura_Fin!Q3-1)),"")) | L4: =IF(COUNT(Captura_Fin!P4,Captura_Fin!H4)<2,"",IF(Captura_Fin!H4<=0,"",Captura_Fin!P4/Captura_Fin!H4)) | M4: =COUNT(E4:K4) | N4: =IF(COUNT(Captura_Fin!F4,Captura_Fin!G4,Captura_Fin!H4)<3,"",IF(ABS(Captura_Fin!F4-Captura_Fin!G4-Captura_Fin!H4)<=0.005*ABS(Captura_Fin!F4),"OK","REVISAR"))
A5: =Captura_Fin!A5 | B5: =Captura_Fin!B5 | C5: =Captura_Fin!C5 | D5: =Captura_Fin!D5 | E5: =IF(COUNT(Captura_Fin!I5,Captura_Fin!J5)<2,"",IFERROR(Captura_Fin!I5/Captura_Fin!J5,"")) | F5: =IF(COUNT(Captura_Fin!M5,Captura_Fin!L5)<2,"",IFERROR(ABS(Captura_Fin!M5)/Captura_Fin!L5,"")) | G5: =IF(COUNT(Captura_Fin!P5,Captura_Fin!F5)<2,"",IFERROR(Captura_Fin!P5/Captura_Fin!F5,"")) | H5: =IF(COUNT(Captura_Fin!G5,Captura_Fin!F5)<2,"",IFERROR(Captura_Fin!G5/Captura_Fin!F5,"")) | I5: =IF(COUNT(Captura_Fin!O5,Captura_Fin!N5)<2,"",IFERROR((Captura_Fin!O5+ABS(Captura_Fin!N5))/ABS(Captura_Fin!N5),"")) | J5: =IF(COUNT(Captura_Fin!L5,Captura_Fin!F5)<2,"",IFERROR(Captura_Fin!L5/Captura_Fin!F5,"")) | K5: =IF(COUNT(Captura_Fin!Q5)<1,"",IFERROR(IF(D5=2017,Captura_Fin!Q5/INDEX(Empresas!$I$2:$I$23,MATCH($A5,Empresas!$B$2:$B$23,0))-1,IF(COUNT(Captura_Fin!Q4)<1,"",Captura_Fin!Q5/Captura_Fin!Q4-1)),"")) | L5: =IF(COUNT(Captura_Fin!P5,Captura_Fin!H5)<2,"",IF(Captura_Fin!H5<=0,"",Captura_Fin!P5/Captura_Fin!H5)) | M5: =COUNT(E5:K5) | N5: =IF(COUNT(Captura_Fin!F5,Captura_Fin!G5,Captura_Fin!H5)<3,"",IF(ABS(Captura_Fin!F5-Captura_Fin!G5-Captura_Fin!H5)<=0.005*ABS(Captura_Fin!F5),"OK","REVISAR"))
A6: =Captura_Fin!A6 | B6: =Captura_Fin!B6 | C6: =Captura_Fin!C6 | D6: =Captura_Fin!D6 | E6: =IF(COUNT(Captura_Fin!I6,Captura_Fin!J6)<2,"",IFERROR(Captura_Fin!I6/Captura_Fin!J6,"")) | F6: =IF(COUNT(Captura_Fin!M6,Captura_Fin!L6)<2,"",IFERROR(ABS(Captura_Fin!M6)/Captura_Fin!L6,"")) | G6: =IF(COUNT(Captura_Fin!P6,Captura_Fin!F6)<2,"",IFERROR(Captura_Fin!P6/Captura_Fin!F6,"")) | H6: =IF(COUNT(Captura_Fin!G6,Captura_Fin!F6)<2,"",IFERROR(Captura_Fin!G6/Captura_Fin!F6,"")) | I6: =IF(COUNT(Captura_Fin!O6,Captura_Fin!N6)<2,"",IFERROR((Captura_Fin!O6+ABS(Captura_Fin!N6))/ABS(Captura_Fin!N6),"")) | J6: =IF(COUNT(Captura_Fin!L6,Captura_Fin!F6)<2,"",IFERROR(Captura_Fin!L6/Captura_Fin!F6,"")) | K6: =IF(COUNT(Captura_Fin!Q6)<1,"",IFERROR(IF(D6=2017,Captura_Fin!Q6/INDEX(Empresas!$I$2:$I$23,MATCH($A6,Empresas!$B$2:$B$23,0))-1,IF(COUNT(Captura_Fin!Q5)<1,"",Captura_Fin!Q6/Captura_Fin!Q5-1)),"")) | L6: =IF(COUNT(Captura_Fin!P6,Captura_Fin!H6)<2,"",IF(Captura_Fin!H6<=0,"",Captura_Fin!P6/Captura_Fin!H6)) | M6: =COUNT(E6:K6) | N6: =IF(COUNT(Captura_Fin!F6,Captura_Fin!G6,Captura_Fin!H6)<3,"",IF(ABS(Captura_Fin!F6-Captura_Fin!G6-Captura_Fin!H6)<=0.005*ABS(Captura_Fin!F6),"OK","REVISAR"))
A7: =Captura_Fin!A7 | B7: =Captura_Fin!B7 | C7: =Captura_Fin!C7 | D7: =Captura_Fin!D7 | E7: =IF(COUNT(Captura_Fin!I7,Captura_Fin!J7)<2,"",IFERROR(Captura_Fin!I7/Captura_Fin!J7,"")) | F7: =IF(COUNT(Captura_Fin!M7,Captura_Fin!L7)<2,"",IFERROR(ABS(Captura_Fin!M7)/Captura_Fin!L7,"")) | G7: =IF(COUNT(Captura_Fin!P7,Captura_Fin!F7)<2,"",IFERROR(Captura_Fin!P7/Captura_Fin!F7,"")) | H7: =IF(COUNT(Captura_Fin!G7,Captura_Fin!F7)<2,"",IFERROR(Captura_Fin!G7/Captura_Fin!F7,"")) | I7: =IF(COUNT(Captura_Fin!O7,Captura_Fin!N7)<2,"",IFERROR((Captura_Fin!O7+ABS(Captura_Fin!N7))/ABS(Captura_Fin!N7),"")) | J7: =IF(COUNT(Captura_Fin!L7,Captura_Fin!F7)<2,"",IFERROR(Captura_Fin!L7/Captura_Fin!F7,"")) | K7: =IF(COUNT(Captura_Fin!Q7)<1,"",IFERROR(IF(D7=2017,Captura_Fin!Q7/INDEX(Empresas!$I$2:$I$23,MATCH($A7,Empresas!$B$2:$B$23,0))-1,IF(COUNT(Captura_Fin!Q6)<1,"",Captura_Fin!Q7/Captura_Fin!Q6-1)),"")) | L7: =IF(COUNT(Captura_Fin!P7,Captura_Fin!H7)<2,"",IF(Captura_Fin!H7<=0,"",Captura_Fin!P7/Captura_Fin!H7)) | M7: =COUNT(E7:K7) | N7: =IF(COUNT(Captura_Fin!F7,Captura_Fin!G7,Captura_Fin!H7)<3,"",IF(ABS(Captura_Fin!F7-Captura_Fin!G7-Captura_Fin!H7)<=0.005*ABS(Captura_Fin!F7),"OK","REVISAR"))
A8: =Captura_Fin!A8 | B8: =Captura_Fin!B8 | C8: =Captura_Fin!C8 | D8: =Captura_Fin!D8 | E8: =IF(COUNT(Captura_Fin!I8,Captura_Fin!J8)<2,"",IFERROR(Captura_Fin!I8/Captura_Fin!J8,"")) | F8: =IF(COUNT(Captura_Fin!M8,Captura_Fin!L8)<2,"",IFERROR(ABS(Captura_Fin!M8)/Captura_Fin!L8,"")) | G8: =IF(COUNT(Captura_Fin!P8,Captura_Fin!F8)<2,"",IFERROR(Captura_Fin!P8/Captura_Fin!F8,"")) | H8: =IF(COUNT(Captura_Fin!G8,Captura_Fin!F8)<2,"",IFERROR(Captura_Fin!G8/Captura_Fin!F8,"")) | I8: =IF(COUNT(Captura_Fin!O8,Captura_Fin!N8)<2,"",IFERROR((Captura_Fin!O8+ABS(Captura_Fin!N8))/ABS(Captura_Fin!N8),"")) | J8: =IF(COUNT(Captura_Fin!L8,Captura_Fin!F8)<2,"",IFERROR(Captura_Fin!L8/Captura_Fin!F8,"")) | K8: =IF(COUNT(Captura_Fin!Q8)<1,"",IFERROR(IF(D8=2017,Captura_Fin!Q8/INDEX(Empresas!$I$2:$I$23,MATCH($A8,Empresas!$B$2:$B$23,0))-1,IF(COUNT(Captura_Fin!Q7)<1,"",Captura_Fin!Q8/Captura_Fin!Q7-1)),"")) | L8: =IF(COUNT(Captura_Fin!P8,Captura_Fin!H8)<2,"",IF(Captura_Fin!H8<=0,"",Captura_Fin!P8/Captura_Fin!H8)) | M8: =COUNT(E8:K8) | N8: =IF(COUNT(Captura_Fin!F8,Captura_Fin!G8,Captura_Fin!H8)<3,"",IF(ABS(Captura_Fin!F8-Captura_Fin!G8-Captura_Fin!H8)<=0.005*ABS(Captura_Fin!F8),"OK","REVISAR"))
A9: =Captura_Fin!A9 | B9: =Captura_Fin!B9 | C9: =Captura_Fin!C9 | D9: =Captura_Fin!D9 | E9: =IF(COUNT(Captura_Fin!I9,Captura_Fin!J9)<2,"",IFERROR(Captura_Fin!I9/Captura_Fin!J9,"")) | F9: =IF(COUNT(Captura_Fin!M9,Captura_Fin!L9)<2,"",IFERROR(ABS(Captura_Fin!M9)/Captura_Fin!L9,"")) | G9: =IF(COUNT(Captura_Fin!P9,Captura_Fin!F9)<2,"",IFERROR(Captura_Fin!P9/Captura_Fin!F9,"")) | H9: =IF(COUNT(Captura_Fin!G9,Captura_Fin!F9)<2,"",IFERROR(Captura_Fin!G9/Captura_Fin!F9,"")) | I9: =IF(COUNT(Captura_Fin!O9,Captura_Fin!N9)<2,"",IFERROR((Captura_Fin!O9+ABS(Captura_Fin!N9))/ABS(Captura_Fin!N9),"")) | J9: =IF(COUNT(Captura_Fin!L9,Captura_Fin!F9)<2,"",IFERROR(Captura_Fin!L9/Captura_Fin!F9,"")) | K9: =IF(COUNT(Captura_Fin!Q9)<1,"",IFERROR(IF(D9=2017,Captura_Fin!Q9/INDEX(Empresas!$I$2:$I$23,MATCH($A9,Empresas!$B$2:$B$23,0))-1,IF(COUNT(Captura_Fin!Q8)<1,"",Captura_Fin!Q9/Captura_Fin!Q8-1)),"")) | L9: =IF(COUNT(Captura_Fin!P9,Captura_Fin!H9)<2,"",IF(Captura_Fin!H9<=0,"",Captura_Fin!P9/Captura_Fin!H9)) | M9: =COUNT(E9:K9) | N9: =IF(COUNT(Captura_Fin!F9,Captura_Fin!G9,Captura_Fin!H9)<3,"",IF(ABS(Captura_Fin!F9-Captura_Fin!G9-Captura_Fin!H9)<=0.005*ABS(Captura_Fin!F9),"OK","REVISAR"))
A10: =Captura_Fin!A10 | B10: =Captura_Fin!B10 | C10: =Captura_Fin!C10 | D10: =Captura_Fin!D10 | E10: =IF(COUNT(Captura_Fin!I10,Captura_Fin!J10)<2,"",IFERROR(Captura_Fin!I10/Captura_Fin!J10,"")) | F10: =IF(COUNT(Captura_Fin!M10,Captura_Fin!L10)<2,"",IFERROR(ABS(Captura_Fin!M10)/Captura_Fin!L10,"")) | G10: =IF(COUNT(Captura_Fin!P10,Captura_Fin!F10)<2,"",IFERROR(Captura_Fin!P10/Captura_Fin!F10,"")) | H10: =IF(COUNT(Captura_Fin!G10,Captura_Fin!F10)<2,"",IFERROR(Captura_Fin!G10/Captura_Fin!F10,"")) | I10: =IF(COUNT(Captura_Fin!O10,Captura_Fin!N10)<2,"",IFERROR((Captura_Fin!O10+ABS(Captura_Fin!N10))/ABS(Captura_Fin!N10),"")) | J10: =IF(COUNT(Captura_Fin!L10,Captura_Fin!F10)<2,"",IFERROR(Captura_Fin!L10/Captura_Fin!F10,"")) | K10: =IF(COUNT(Captura_Fin!Q10)<1,"",IFERROR(IF(D10=2017,Captura_Fin!Q10/INDEX(Empresas!$I$2:$I$23,MATCH($A10,Empresas!$B$2:$B$23,0))-1,IF(COUNT(Captura_Fin!Q9)<1,"",Captura_Fin!Q10/Captura_Fin!Q9-1)),"")) | L10: =IF(COUNT(Captura_Fin!P10,Captura_Fin!H10)<2,"",IF(Captura_Fin!H10<=0,"",Captura_Fin!P10/Captura_Fin!H10)) | M10: =COUNT(E10:K10) | N10: =IF(COUNT(Captura_Fin!F10,Captura_Fin!G10,Captura_Fin!H10)<3,"",IF(ABS(Captura_Fin!F10-Captura_Fin!G10-Captura_Fin!H10)<=0.005*ABS(Captura_Fin!F10),"OK","REVISAR"))
A11: =Captura_Fin!A11 | B11: =Captura_Fin!B11 | C11: =Captura_Fin!C11 | D11: =Captura_Fin!D11 | E11: =IF(COUNT(Captura_Fin!I11,Captura_Fin!J11)<2,"",IFERROR(Captura_Fin!I11/Captura_Fin!J11,"")) | F11: =IF(COUNT(Captura_Fin!M11,Captura_Fin!L11)<2,"",IFERROR(ABS(Captura_Fin!M11)/Captura_Fin!L11,"")) | G11: =IF(COUNT(Captura_Fin!P11,Captura_Fin!F11)<2,"",IFERROR(Captura_Fin!P11/Captura_Fin!F11,"")) | H11: =IF(COUNT(Captura_Fin!G11,Captura_Fin!F11)<2,"",IFERROR(Captura_Fin!G11/Captura_Fin!F11,"")) | I11: =IF(COUNT(Captura_Fin!O11,Captura_Fin!N11)<2,"",IFERROR((Captura_Fin!O11+ABS(Captura_Fin!N11))/ABS(Captura_Fin!N11),"")) | J11: =IF(COUNT(Captura_Fin!L11,Captura_Fin!F11)<2,"",IFERROR(Captura_Fin!L11/Captura_Fin!F11,"")) | K11: =IF(COUNT(Captura_Fin!Q11)<1,"",IFERROR(IF(D11=2017,Captura_Fin!Q11/INDEX(Empresas!$I$2:$I$23,MATCH($A11,Empresas!$B$2:$B$23,0))-1,IF(COUNT(Captura_Fin!Q10)<1,"",Captura_Fin!Q11/Captura_Fin!Q10-1)),"")) | L11: =IF(COUNT(Captura_Fin!P11,Captura_Fin!H11)<2,"",IF(Captura_Fin!H11<=0,"",Captura_Fin!P11/Captura_Fin!H11)) | M11: =COUNT(E11:K11) | N11: =IF(COUNT(Captura_Fin!F11,Captura_Fin!G11,Captura_Fin!H11)<3,"",IF(ABS(Captura_Fin!F11-Captura_Fin!G11-Captura_Fin!H11)<=0.005*ABS(Captura_Fin!F11),"OK","REVISAR"))
A12: =Captura_Fin!A12 | B12: =Captura_Fin!B12 | C12: =Captura_Fin!C12 | D12: =Captura_Fin!D12 | E12: =IF(COUNT(Captura_Fin!I12,Captura_Fin!J12)<2,"",IFERROR(Captura_Fin!I12/Captura_Fin!J12,"")) | F12: =IF(COUNT(Captura_Fin!M12,Captura_Fin!L12)<2,"",IFERROR(ABS(Captura_Fin!M12)/Captura_Fin!L12,"")) | G12: =IF(COUNT(Captura_Fin!P12,Captura_Fin!F12)<2,"",IFERROR(Captura_Fin!P12/Captura_Fin!F12,"")) | H12: =IF(COUNT(Captura_Fin!G12,Captura_Fin!F12)<2,"",IFERROR(Captura_Fin!G12/Captura_Fin!F12,"")) | I12: =IF(COUNT(Captura_Fin!O12,Captura_Fin!N12)<2,"",IFERROR((Captura_Fin!O12+ABS(Captura_Fin!N12))/ABS(Captura_Fin!N12),"")) | J12: =IF(COUNT(Captura_Fin!L12,Captura_Fin!F12)<2,"",IFERROR(Captura_Fin!L12/Captura_Fin!F12,"")) | K12: =IF(COUNT(Captura_Fin!Q12)<1,"",IFERROR(IF(D12=2017,Captura_Fin!Q12/INDEX(Empresas!$I$2:$I$23,MATCH($A12,Empresas!$B$2:$B$23,0))-1,IF(COUNT(Captura_Fin!Q11)<1,"",Captura_Fin!Q12/Captura_Fin!Q11-1)),"")) | L12: =IF(COUNT(Captura_Fin!P12,Captura_Fin!H12)<2,"",IF(Captura_Fin!H12<=0,"",Captura_Fin!P12/Captura_Fin!H12)) | M12: =COUNT(E12:K12) | N12: =IF(COUNT(Captura_Fin!F12,Captura_Fin!G12,Captura_Fin!H12)<3,"",IF(ABS(Captura_Fin!F12-Captura_Fin!G12-Captura_Fin!H12)<=0.005*ABS(Captura_Fin!F12),"OK","REVISAR"))
A13: =Captura_Fin!A13 | B13: =Captura_Fin!B13 | C13: =Captura_Fin!C13 | D13: =Captura_Fin!D13 | E13: =IF(COUNT(Captura_Fin!I13,Captura_Fin!J13)<2,"",IFERROR(Captura_Fin!I13/Captura_Fin!J13,"")) | F13: =IF(COUNT(Captura_Fin!M13,Captura_Fin!L13)<2,"",IFERROR(ABS(Captura_Fin!M13)/Captura_Fin!L13,"")) | G13: =IF(COUNT(Captura_Fin!P13,Captura_Fin!F13)<2,"",IFERROR(Captura_Fin!P13/Captura_Fin!F13,"")) | H13: =IF(COUNT(Captura_Fin!G13,Captura_Fin!F13)<2,"",IFERROR(Captura_Fin!G13/Captura_Fin!F13,"")) | I13: =IF(COUNT(Captura_Fin!O13,Captura_Fin!N13)<2,"",IFERROR((Captura_Fin!O13+ABS(Captura_Fin!N13))/ABS(Captura_Fin!N13),"")) | J13: =IF(COUNT(Captura_Fin!L13,Captura_Fin!F13)<2,"",IFERROR(Captura_Fin!L13/Captura_Fin!F13,"")) | K13: =IF(COUNT(Captura_Fin!Q13)<1,"",IFERROR(IF(D13=2017,Captura_Fin!Q13/INDEX(Empresas!$I$2:$I$23,MATCH($A13,Empresas!$B$2:$B$23,0))-1,IF(COUNT(Captura_Fin!Q12)<1,"",Captura_Fin!Q13/Captura_Fin!Q12-1)),"")) | L13: =IF(COUNT(Captura_Fin!P13,Captura_Fin!H13)<2,"",IF(Captura_Fin!H13<=0,"",Captura_Fin!P13/Captura_Fin!H13)) | M13: =COUNT(E13:K13) | N13: =IF(COUNT(Captura_Fin!F13,Captura_Fin!G13,Captura_Fin!H13)<3,"",IF(ABS(Captura_Fin!F13-Captura_Fin!G13-Captura_Fin!H13)<=0.005*ABS(Captura_Fin!F13),"OK","REVISAR"))
... A37: =Captura_Fin!A37 | B37: =Captura_Fin!B37 | C37: =Captura_Fin!C37 | D37: =Captura_Fin!D37 | E37: =IF(COUNT(Captura_Fin!I37,Captura_Fin!J37)<2,"",IFERROR(Captura_Fin!I37/Captura_Fin!J37,"")) | F37: =IF(COUNT(Captura_Fin!M37,Captura_Fin!L37)<2,"",IFERROR(ABS(Captura_Fin!M37)/Captura_Fin!L37,"")) | G37: =IF(COUNT(Captura_Fin!P37,Captura_Fin!F37)<2,"",IFERROR(Captura_Fin!P37/Captura_Fin!F37,"")) | H37: =IF(COUNT(Captura_Fin!G37,Captura_Fin!F37)<2,"",IFERROR(Captura_Fin!G37/Captura_Fin!F37,"")) | I37: =IF(COUNT(Captura_Fin!O37,Captura_Fin!N37)<2,"",IFERROR((Captura_Fin!O37+ABS(Captura_Fin!N37))/ABS(Captura_Fin!N37),"")) | J37: =IF(COUNT(Captura_Fin!L37,Captura_Fin!F37)<2,"",IFERROR(Captura_Fin!L37/Captura_Fin!F37,"")) | K37: =IF(COUNT(Captura_Fin!Q37)<1,"",IFERROR(IF(D37=2017,Captura_Fin!Q37/INDEX(Empresas!$I$2:$I$23,MATCH($A37,Empresas!$B$2:$B$23,0))-1,IF(COUNT(Captura_Fin!Q36)<1,"",Captura_Fin!Q37/Captura_Fin!Q36-1)),"")) | L37: =IF(COUNT(Captura_Fin!P37,Captura_Fin!H37)<2,"",IF(Captura_Fin!H37<=0,"",Captura_Fin!P37/Captura_Fin!H37)) | M37: =COUNT(E37:K37) | N37: =IF(COUNT(Captura_Fin!F37,Captura_Fin!G37,Captura_Fin!H37)<3,"",IF(ABS(Captura_Fin!F37-Captura_Fin!G37-Captura_Fin!H37)<=0.005*ABS(Captura_Fin!F37),"OK","REVISAR"))
A39: F2 Capital de trabajo no aplica a bancos: sus estados financieros no clasifican partidas en corrientes y no corrientes. El KPI de este sector se construye con 7 familias.
A40: F3 Eficiencia bancaria = índice de eficiencia (gastos operacionales / ingresos operacionales netos): dirección MAYOR = PEOR, a diferencia del margen de las no financieras.
A41: F6 Cobertura bancaria = (resultado antes de impuestos + provisiones) / provisiones: veces que el resultado antes de provisiones cubre el costo del riesgo de crédito.

Sheet Direccion
A1: Familia | B1: No financieras: indicador | C1: Dirección | D1: Signo en Fase 3 | E1: Bancos: indicador | F1: Dirección | G1: Signo en Fase 3
A2: F1 Liquidez | B2: Activo corriente / Pasivo corriente | C2: Mayor = mejor | D2: 1 | E2: Efectivo / Depósitos | F2: Mayor = mejor | G2: 1
A3: F2 Capital de trabajo | B3: (AC − PC) / Activo total | C3: Mayor = mejor | D3: 1 | E3: No aplica | F3: —
A4: F3 Eficiencia | B4: EBIT / Ingresos | C4: Mayor = mejor | D4: 1 | E4: Gastos operacionales / Ingreso operacional neto | F4: Mayor = peor | G4: -1
A5: F4 Rentabilidad | B5: Ganancia / Activo total (ROA) | C5: Mayor = mejor | D5: 1 | E5: Ganancia / Activo total (ROA) | F5: Mayor = mejor | G5: 1
A6: F5 Endeudamiento | B6: Pasivo total / Activo total | C6: Mayor = peor | D6: -1 | E6: Pasivo total / Activo total | F6: Mayor = peor | G6: -1
A7: F6 Cobertura | B7: EBIT / Costos financieros | C7: Mayor = mejor | D7: 1 | E7: (GAI + Provisiones) / Provisiones | F7: Mayor = mejor | G7: 1
A8: F7 Uso de activos | B8: Ingresos / Activo total | C8: Mayor = mejor | D8: 1 | E8: Ingreso operacional neto / Activo total | F8: Mayor = mejor | G8: 1
A9: F8 Mercado | B9: Retorno anual del precio ajustado | C9: Mayor = mejor | D9: 1 | E9: Retorno anual del precio ajustado | F9: Mayor = mejor | G9: 1
A11: El signo se aplica en la Fase 3: z orientado = signo × z. Así, en todas las familias un valor mayor indica mejor condición antes de promediar en el KPI.

Sheet Control
A1: Nemotécnico | B1: Plantilla | C1: Años con activo total | D1: Celdas núcleo vacías | E1: Años cuadre REVISAR | F1: Familias válidas (promedio) | G1: Estado
A2: AGUAS-A | B2: No financiera | C2: =COUNTIFS(Captura_NoFin!$A$2:$A$163,$A2,Captura_NoFin!$H$2:$H$163,"<>") | D2: =COUNTIFS(Captura_NoFin!$A$2:$A$163,$A2,Captura_NoFin!$F$2:$F$163,"")+COUNTIFS(Captura_NoFin!$A$2:$A$163,$A2,Captura_NoFin!$G$2:$G$163,"")+COUNTIFS(Captura_NoFin!$A$2:$A$163,$A2,Captura_NoFin!$H$2:$H$163,"")+COUNTIFS(Captura_NoFin!$A$2:$A$163,$A2,Captura_NoFin!$I$2:$I$163,"")+COUNTIFS(Captura_NoFin!$A$2:$A$163,$A2,Captura_NoFin!$J$2:$J$163,"")+COUNTIFS(Captura_NoFin!$A$2:$A$163,$A2,Captura_NoFin!$K$2:$K$163,"")+COUNTIFS(Captura_NoFin!$A$2:$A$163,$A2,Captura_NoFin!$L$2:$L$163,"")+COUNTIFS(Captura_NoFin!$A$2:$A$163,$A2,Captura_NoFin!$M$2:$M$163,"")+COUNTIFS(Captura_NoFin!$A$2:$A$163,$A2,Captura_NoFin!$N$2:$N$163,"")+COUNTIFS(Captura_NoFin!$A$2:$A$163,$A2,Captura_NoFin!$R$2:$R$163,"") | E2: =COUNTIFS(Ratios_NoFin!$A$2:$A$163,$A2,Ratios_NoFin!$P$2:$P$163,"REVISAR") | F2: =IFERROR(AVERAGEIFS(Ratios_NoFin!$O$2:$O$163,Ratios_NoFin!$A$2:$A$163,$A2),0) | G2: =IF(D2=0,IF(E2=0,"COMPLETA","REVISAR CUADRE"),"PENDIENTE")
A3: COLBUN | B3: No financiera | C3: =COUNTIFS(Captura_NoFin!$A$2:$A$163,$A3,Captura_NoFin!$H$2:$H$163,"<>") | D3: =COUNTIFS(Captura_NoFin!$A$2:$A$163,$A3,Captura_NoFin!$F$2:$F$163,"")+COUNTIFS(Captura_NoFin!$A$2:$A$163,$A3,Captura_NoFin!$G$2:$G$163,"")+COUNTIFS(Captura_NoFin!$A$2:$A$163,$A3,Captura_NoFin!$H$2:$H$163,"")+COUNTIFS(Captura_NoFin!$A$2:$A$163,$A3,Captura_NoFin!$I$2:$I$163,"")+COUNTIFS(Captura_NoFin!$A$2:$A$163,$A3,Captura_NoFin!$J$2:$J$163,"")+COUNTIFS(Captura_NoFin!$A$2:$A$163,$A3,Captura_NoFin!$K$2:$K$163,"")+COUNTIFS(Captura_NoFin!$A$2:$A$163,$A3,Captura_NoFin!$L$2:$L$163,"")+COUNTIFS(Captura_NoFin!$A$2:$A$163,$A3,Captura_NoFin!$M$2:$M$163,"")+COUNTIFS(Captura_NoFin!$A$2:$A$163,$A3,Captura_NoFin!$N$2:$N$163,"")+COUNTIFS(Captura_NoFin!$A$2:$A$163,$A3,Captura_NoFin!$R$2:$R$163,"") | E3: =COUNTIFS(Ratios_NoFin!$A$2:$A$163,$A3,Ratios_NoFin!$P$2:$P$163,"REVISAR") | F3: =IFERROR(AVERAGEIFS(Ratios_NoFin!$O$2:$O$163,Ratios_NoFin!$A$2:$A$163,$A3),0) | G3: =IF(D3=0,IF(E3=0,"COMPLETA","REVISAR CUADRE"),"PENDIENTE")
A4: ENELAM | B4: No financiera | C4: =COUNTIFS(Captura_NoFin!$A$2:$A$163,$A4,Captura_NoFin!$H$2:$H$163,"<>") | D4: =COUNTIFS(Captura_NoFin!$A$2:$A$163,$A4,Captura_NoFin!$F$2:$F$163,"")+COUNTIFS(Captura_NoFin!$A$2:$A$163,$A4,Captura_NoFin!$G$2:$G$163,"")+COUNTIFS(Captura_NoFin!$A$2:$A$163,$A4,Captura_NoFin!$H$2:$H$163,"")+COUNTIFS(Captura_NoFin!$A$2:$A$163,$A4,Captura_NoFin!$I$2:$I$163,"")+COUNTIFS(Captura_NoFin!$A$2:$A$163,$A4,Captura_NoFin!$J$2:$J$163,"")+COUNTIFS(Captura_NoFin!$A$2:$A$163,$A4,Captura_NoFin!$K$2:$K$163,"")+COUNTIFS(Captura_NoFin!$A$2:$A$163,$A4,Captura_NoFin!$L$2:$L$163,"")+COUNTIFS(Captura_NoFin!$A$2:$A$163,$A4,Captura_NoFin!$M$2:$M$163,"")+COUNTIFS(Captura_NoFin!$A$2:$A$163,$A4,Captura_NoFin!$N$2:$N$163,"")+COUNTIFS(Captura_NoFin!$A$2:$A$163,$A4,Captura_NoFin!$R$2:$R$163,"") | E4: =COUNTIFS(Ratios_NoFin!$A$2:$A$163,$A4,Ratios_NoFin!$P$2:$P$163,"REVISAR") | F4: =IFERROR(AVERAGEIFS(Ratios_NoFin!$O$2:$O$163,Ratios_NoFin!$A$2:$A$163,$A4),0) | G4: =IF(D4=0,IF(E4=0,"COMPLETA","REVISAR CUADRE"),"PENDIENTE")
A5: ENELCHILE | B5: No financiera | C5: =COUNTIFS(Captura_NoFin!$A$2:$A$163,$A5,Captura_NoFin!$H$2:$H$163,"<>") | D5: =COUNTIFS(Captura_NoFin!$A$2:$A$163,$A5,Captura_NoFin!$F$2:$F$163,"")+COUNTIFS(Captura_NoFin!$A$2:$A$163,$A5,Captura_NoFin!$G$2:$G$163,"")+COUNTIFS(Captura_NoFin!$A$2:$A$163,$A5,Captura_NoFin!$H$2:$H$163,"")+COUNTIFS(Captura_NoFin!$A$2:$A$163,$A5,Captura_NoFin!$I$2:$I$163,"")+COUNTIFS(Captura_NoFin!$A$2:$A$163,$A5,Captura_NoFin!$J$2:$J$163,"")+COUNTIFS(Captura_NoFin!$A$2:$A$163,$A5,Captura_NoFin!$K$2:$K$163,"")+COUNTIFS(Captura_NoFin!$A$2:$A$163,$A5,Captura_NoFin!$L$2:$L$163,"")+COUNTIFS(Captura_NoFin!$A$2:$A$163,$A5,Captura_NoFin!$M$2:$M$163,"")+COUNTIFS(Captura_NoFin!$A$2:$A$163,$A5,Captura_NoFin!$N$2:$N$163,"")+COUNTIFS(Captura_NoFin!$A$2:$A$163,$A5,Captura_NoFin!$R$2:$R$163,"") | E5: =COUNTIFS(Ratios_NoFin!$A$2:$A$163,$A5,Ratios_NoFin!$P$2:$P$163,"REVISAR") | F5: =IFERROR(AVERAGEIFS(Ratios_NoFin!$O$2:$O$163,Ratios_NoFin!$A$2:$A$163,$A5),0) | G5: =IF(D5=0,IF(E5=0,"COMPLETA","REVISAR CUADRE"),"PENDIENTE")
A6: ECL | B6: No financiera | C6: =COUNTIFS(Captura_NoFin!$A$2:$A$163,$A6,Captura_NoFin!$H$2:$H$163,"<>") | D6: =COUNTIFS(Captura_NoFin!$A$2:$A$163,$A6,Captura_NoFin!$F$2:$F$163,"")+COUNTIFS(Captura_NoFin!$A$2:$A$163,$A6,Captura_NoFin!$G$2:$G$163,"")+COUNTIFS(Captura_NoFin!$A$2:$A$163,$A6,Captura_NoFin!$H$2:$H$163,"")+COUNTIFS(Captura_NoFin!$A$2:$A$163,$A6,Captura_NoFin!$I$2:$I$163,"")+COUNTIFS(Captura_NoFin!$A$2:$A$163,$A6,Captura_NoFin!$J$2:$J$163,"")+COUNTIFS(Captura_NoFin!$A$2:$A$163,$A6,Captura_NoFin!$K$2:$K$163,"")+COUNTIFS(Captura_NoFin!$A$2:$A$163,$A6,Captura_NoFin!$L$2:$L$163,"")+COUNTIFS(Captura_NoFin!$A$2:$A$163,$A6,Captura_NoFin!$M$2:$M$163,"")+COUNTIFS(Captura_NoFin!$A$2:$A$163,$A6,Captura_NoFin!$N$2:$N$163,"")+COUNTIFS(Captura_NoFin!$A$2:$A$163,$A6,Captura_NoFin!$R$2:$R$163,"") | E6: =COUNTIFS(Ratios_NoFin!$A$2:$A$163,$A6,Ratios_NoFin!$P$2:$P$163,"REVISAR") | F6: =IFERROR(AVERAGEIFS(Ratios_NoFin!$O$2:$O$163,Ratios_NoFin!$A$2:$A$163,$A6),0) | G6: =IF(D6=0,IF(E6=0,"COMPLETA","REVISAR CUADRE"),"PENDIENTE")
A7: ENTEL | B7: No financiera | C7: =COUNTIFS(Captura_NoFin!$A$2:$A$163,$A7,Captura_NoFin!$H$2:$H$163,"<>") | D7: =COUNTIFS(Captura_NoFin!$A$2:$A$163,$A7,Captura_NoFin!$F$2:$F$163,"")+COUNTIFS(Captura_NoFin!$A$2:$A$163,$A7,Captura_NoFin!$G$2:$G$163,"")+COUNTIFS(Captura_NoFin!$A$2:$A$163,$A7,Captura_NoFin!$H$2:$H$163,"")+COUNTIFS(Captura_NoFin!$A$2:$A$163,$A7,Captura_NoFin!$I$2:$I$163,"")+COUNTIFS(Captura_NoFin!$A$2:$A$163,$A7,Captura_NoFin!$J$2:$J$163,"")+COUNTIFS(Captura_NoFin!$A$2:$A$163,$A7,Captura_NoFin!$K$2:$K$163,"")+COUNTIFS(Captura_NoFin!$A$2:$A$163,$A7,Captura_NoFin!$L$2:$L$163,"")+COUNTIFS(Captura_NoFin!$A$2:$A$163,$A7,Captura_NoFin!$M$2:$M$163,"")+COUNTIFS(Captura_NoFin!$A$2:$A$163,$A7,Captura_NoFin!$N$2:$N$163,"")+COUNTIFS(Captura_NoFin!$A$2:$A$163,$A7,Captura_NoFin!$R$2:$R$163,"") | E7: =COUNTIFS(Ratios_NoFin!$A$2:$A$163,$A7,Ratios_NoFin!$P$2:$P$163,"REVISAR") | F7: =IFERROR(AVERAGEIFS(Ratios_NoFin!$O$2:$O$163,Ratios_NoFin!$A$2:$A$163,$A7),0) | G7: =IF(D7=0,IF(E7=0,"COMPLETA","REVISAR CUADRE"),"PENDIENTE")
A8: CENCOSUD | B8: No financiera | C8: =COUNTIFS(Captura_NoFin!$A$2:$A$163,$A8,Captura_NoFin!$H$2:$H$163,"<>") | D8: =COUNTIFS(Captura_NoFin!$A$2:$A$163,$A8,Captura_NoFin!$F$2:$F$163,"")+COUNTIFS(Captura_NoFin!$A$2:$A$163,$A8,Captura_NoFin!$G$2:$G$163,"")+COUNTIFS(Captura_NoFin!$A$2:$A$163,$A8,Captura_NoFin!$H$2:$H$163,"")+COUNTIFS(Captura_NoFin!$A$2:$A$163,$A8,Captura_NoFin!$I$2:$I$163,"")+COUNTIFS(Captura_NoFin!$A$2:$A$163,$A8,Captura_NoFin!$J$2:$J$163,"")+COUNTIFS(Captura_NoFin!$A$2:$A$163,$A8,Captura_NoFin!$K$2:$K$163,"")+COUNTIFS(Captura_NoFin!$A$2:$A$163,$A8,Captura_NoFin!$L$2:$L$163,"")+COUNTIFS(Captura_NoFin!$A$2:$A$163,$A8,Captura_NoFin!$M$2:$M$163,"")+COUNTIFS(Captura_NoFin!$A$2:$A$163,$A8,Captura_NoFin!$N$2:$N$163,"")+COUNTIFS(Captura_NoFin!$A$2:$A$163,$A8,Captura_NoFin!$R$2:$R$163,"") | E8: =COUNTIFS(Ratios_NoFin!$A$2:$A$163,$A8,Ratios_NoFin!$P$2:$P$163,"REVISAR") | F8: =IFERROR(AVERAGEIFS(Ratios_NoFin!$O$2:$O$163,Ratios_NoFin!$A$2:$A$163,$A8),0) | G8: =IF(D8=0,IF(E8=0,"COMPLETA","REVISAR CUADRE"),"PENDIENTE")
A9: FALABELLA | B9: No financiera | C9: =COUNTIFS(Captura_NoFin!$A$2:$A$163,$A9,Captura_NoFin!$H$2:$H$163,"<>") | D9: =COUNTIFS(Captura_NoFin!$A$2:$A$163,$A9,Captura_NoFin!$F$2:$F$163,"")+COUNTIFS(Captura_NoFin!$A$2:$A$163,$A9,Captura_NoFin!$G$2:$G$163,"")+COUNTIFS(Captura_NoFin!$A$2:$A$163,$A9,Captura_NoFin!$H$2:$H$163,"")+COUNTIFS(Captura_NoFin!$A$2:$A$163,$A9,Captura_NoFin!$I$2:$I$163,"")+COUNTIFS(Captura_NoFin!$A$2:$A$163,$A9,Captura_NoFin!$J$2:$J$163,"")+COUNTIFS(Captura_NoFin!$A$2:$A$163,$A9,Captura_NoFin!$K$2:$K$163,"")+COUNTIFS(Captura_NoFin!$A$2:$A$163,$A9,Captura_NoFin!$L$2:$L$163,"")+COUNTIFS(Captura_NoFin!$A$2:$A$163,$A9,Captura_NoFin!$M$2:$M$163,"")+COUNTIFS(Captura_NoFin!$A$2:$A$163,$A9,Captura_NoFin!$N$2:$N$163,"")+COUNTIFS(Captura_NoFin!$A$2:$A$163,$A9,Captura_NoFin!$R$2:$R$163,"") | E9: =COUNTIFS(Ratios_NoFin!$A$2:$A$163,$A9,Ratios_NoFin!$P$2:$P$163,"REVISAR") | F9: =IFERROR(AVERAGEIFS(Ratios_NoFin!$O$2:$O$163,Ratios_NoFin!$A$2:$A$163,$A9),0) | G9: =IF(D9=0,IF(E9=0,"COMPLETA","REVISAR CUADRE"),"PENDIENTE")
A10: RIPLEY | B10: No financiera | C10: =COUNTIFS(Captura_NoFin!$A$2:$A$163,$A10,Captura_NoFin!$H$2:$H$163,"<>") | D10: =COUNTIFS(Captura_NoFin!$A$2:$A$163,$A10,Captura_NoFin!$F$2:$F$163,"")+COUNTIFS(Captura_NoFin!$A$2:$A$163,$A10,Captura_NoFin!$G$2:$G$163,"")+COUNTIFS(Captura_NoFin!$A$2:$A$163,$A10,Captura_NoFin!$H$2:$H$163,"")+COUNTIFS(Captura_NoFin!$A$2:$A$163,$A10,Captura_NoFin!$I$2:$I$163,"")+COUNTIFS(Captura_NoFin!$A$2:$A$163,$A10,Captura_NoFin!$J$2:$J$163,"")+COUNTIFS(Captura_NoFin!$A$2:$A$163,$A10,Captura_NoFin!$K$2:$K$163,"")+COUNTIFS(Captura_NoFin!$A$2:$A$163,$A10,Captura_NoFin!$L$2:$L$163,"")+COUNTIFS(Captura_NoFin!$A$2:$A$163,$A10,Captura_NoFin!$M$2:$M$163,"")+COUNTIFS(Captura_NoFin!$A$2:$A$163,$A10,Captura_NoFin!$N$2:$N$163,"")+COUNTIFS(Captura_NoFin!$A$2:$A$163,$A10,Captura_NoFin!$R$2:$R$163,"") | E10: =COUNTIFS(Ratios_NoFin!$A$2:$A$163,$A10,Ratios_NoFin!$P$2:$P$163,"REVISAR") | F10: =IFERROR(AVERAGEIFS(Ratios_NoFin!$O$2:$O$163,Ratios_NoFin!$A$2:$A$163,$A10),0) | G10: =IF(D10=0,IF(E10=0,"COMPLETA","REVISAR CUADRE"),"PENDIENTE")
A11: CCU | B11: No financiera | C11: =COUNTIFS(Captura_NoFin!$A$2:$A$163,$A11,Captura_NoFin!$H$2:$H$163,"<>") | D11: =COUNTIFS(Captura_NoFin!$A$2:$A$163,$A11,Captura_NoFin!$F$2:$F$163,"")+COUNTIFS(Captura_NoFin!$A$2:$A$163,$A11,Captura_NoFin!$G$2:$G$163,"")+COUNTIFS(Captura_NoFin!$A$2:$A$163,$A11,Captura_NoFin!$H$2:$H$163,"")+COUNTIFS(Captura_NoFin!$A$2:$A$163,$A11,Captura_NoFin!$I$2:$I$163,"")+COUNTIFS(Captura_NoFin!$A$2:$A$163,$A11,Captura_NoFin!$J$2:$J$163,"")+COUNTIFS(Captura_NoFin!$A$2:$A$163,$A11,Captura_NoFin!$K$2:$K$163,"")+COUNTIFS(Captura_NoFin!$A$2:$A$163,$A11,Captura_NoFin!$L$2:$L$163,"")+COUNTIFS(Captura_NoFin!$A$2:$A$163,$A11,Captura_NoFin!$M$2:$M$163,"")+COUNTIFS(Captura_NoFin!$A$2:$A$163,$A11,Captura_NoFin!$N$2:$N$163,"")+COUNTIFS(Captura_NoFin!$A$2:$A$163,$A11,Captura_NoFin!$R$2:$R$163,"") | E11: =COUNTIFS(Ratios_NoFin!$A$2:$A$163,$A11,Ratios_NoFin!$P$2:$P$163,"REVISAR") | F11: =IFERROR(AVERAGEIFS(Ratios_NoFin!$O$2:$O$163,Ratios_NoFin!$A$2:$A$163,$A11),0) | G11: =IF(D11=0,IF(E11=0,"COMPLETA","REVISAR CUADRE"),"PENDIENTE")
A12: ANDINA-B | B12: No financiera | C12: =COUNTIFS(Captura_NoFin!$A$2:$A$163,$A12,Captura_NoFin!$H$2:$H$163,"<>") | D12: =COUNTIFS(Captura_NoFin!$A$2:$A$163,$A12,Captura_NoFin!$F$2:$F$163,"")+COUNTIFS(Captura_NoFin!$A$2:$A$163,$A12,Captura_NoFin!$G$2:$G$163,"")+COUNTIFS(Captura_NoFin!$A$2:$A$163,$A12,Captura_NoFin!$H$2:$H$163,"")+COUNTIFS(Captura_NoFin!$A$2:$A$163,$A12,Captura_NoFin!$I$2:$I$163,"")+COUNTIFS(Captura_NoFin!$A$2:$A$163,$A12,Captura_NoFin!$J$2:$J$163,"")+COUNTIFS(Captura_NoFin!$A$2:$A$163,$A12,Captura_NoFin!$K$2:$K$163,"")+COUNTIFS(Captura_NoFin!$A$2:$A$163,$A12,Captura_NoFin!$L$2:$L$163,"")+COUNTIFS(Captura_NoFin!$A$2:$A$163,$A12,Captura_NoFin!$M$2:$M$163,"")+COUNTIFS(Captura_NoFin!$A$2:$A$163,$A12,Captura_NoFin!$N$2:$N$163,"")+COUNTIFS(Captura_NoFin!$A$2:$A$163,$A12,Captura_NoFin!$R$2:$R$163,"") | E12: =COUNTIFS(Ratios_NoFin!$A$2:$A$163,$A12,Ratios_NoFin!$P$2:$P$163,"REVISAR") | F12: =IFERROR(AVERAGEIFS(Ratios_NoFin!$O$2:$O$163,Ratios_NoFin!$A$2:$A$163,$A12),0) | G12: =IF(D12=0,IF(E12=0,"COMPLETA","REVISAR CUADRE"),"PENDIENTE")
A13: CONCHATORO | B13: No financiera | C13: =COUNTIFS(Captura_NoFin!$A$2:$A$163,$A13,Captura_NoFin!$H$2:$H$163,"<>") | D13: =COUNTIFS(Captura_NoFin!$A$2:$A$163,$A13,Captura_NoFin!$F$2:$F$163,"")+COUNTIFS(Captura_NoFin!$A$2:$A$163,$A13,Captura_NoFin!$G$2:$G$163,"")+COUNTIFS(Captura_NoFin!$A$2:$A$163,$A13,Captura_NoFin!$H$2:$H$163,"")+COUNTIFS(Captura_NoFin!$A$2:$A$163,$A13,Captura_NoFin!$I$2:$I$163,"")+COUNTIFS(Captura_NoFin!$A$2:$A$163,$A13,Captura_NoFin!$J$2:$J$163,"")+COUNTIFS(Captura_NoFin!$A$2:$A$163,$A13,Captura_NoFin!$K$2:$K$163,"")+COUNTIFS(Captura_NoFin!$A$2:$A$163,$A13,Captura_NoFin!$L$2:$L$163,"")+COUNTIFS(Captura_NoFin!$A$2:$A$163,$A13,Captura_NoFin!$M$2:$M$163,"")+COUNTIFS(Captura_NoFin!$A$2:$A$163,$A13,Captura_NoFin!$N$2:$N$163,"")+COUNTIFS(Captura_NoFin!$A$2:$A$163,$A13,Captura_NoFin!$R$2:$R$163,"") | E13: =COUNTIFS(Ratios_NoFin!$A$2:$A$163,$A13,Ratios_NoFin!$P$2:$P$163,"REVISAR") | F13: =IFERROR(AVERAGEIFS(Ratios_NoFin!$O$2:$O$163,Ratios_NoFin!$A$2:$A$163,$A13),0) | G13: =IF(D13=0,IF(E13=0,"COMPLETA","REVISAR CUADRE"),"PENDIENTE")
... A19: COPEC | B19: No financiera | C19: =COUNTIFS(Captura_NoFin!$A$2:$A$163,$A19,Captura_NoFin!$H$2:$H$163,"<>") | D19: =COUNTIFS(Captura_NoFin!$A$2:$A$163,$A19,Captura_NoFin!$F$2:$F$163,"")+COUNTIFS(Captura_NoFin!$A$2:$A$163,$A19,Captura_NoFin!$G$2:$G$163,"")+COUNTIFS(Captura_NoFin!$A$2:$A$163,$A19,Captura_NoFin!$H$2:$H$163,"")+COUNTIFS(Captura_NoFin!$A$2:$A$163,$A19,Captura_NoFin!$I$2:$I$163,"")+COUNTIFS(Captura_NoFin!$A$2:$A$163,$A19,Captura_NoFin!$J$2:$J$163,"")+COUNTIFS(Captura_NoFin!$A$2:$A$163,$A19,Captura_NoFin!$K$2:$K$163,"")+COUNTIFS(Captura_NoFin!$A$2:$A$163,$A19,Captura_NoFin!$L$2:$L$163,"")+COUNTIFS(Captura_NoFin!$A$2:$A$163,$A19,Captura_NoFin!$M$2:$M$163,"")+COUNTIFS(Captura_NoFin!$A$2:$A$163,$A19,Captura_NoFin!$N$2:$N$163,"")+COUNTIFS(Captura_NoFin!$A$2:$A$163,$A19,Captura_NoFin!$R$2:$R$163,"") | E19: =COUNTIFS(Ratios_NoFin!$A$2:$A$163,$A19,Ratios_NoFin!$P$2:$P$163,"REVISAR") | F19: =IFERROR(AVERAGEIFS(Ratios_NoFin!$O$2:$O$163,Ratios_NoFin!$A$2:$A$163,$A19),0) | G19: =IF(D19=0,IF(E19=0,"COMPLETA","REVISAR CUADRE"),"PENDIENTE")
A20: CHILE | B20: Financiera | C20: =COUNTIFS(Captura_Fin!$A$2:$A$37,$A20,Captura_Fin!$F$2:$F$37,"<>") | D20: =COUNTIFS(Captura_Fin!$A$2:$A$37,$A20,Captura_Fin!$F$2:$F$37,"")+COUNTIFS(Captura_Fin!$A$2:$A$37,$A20,Captura_Fin!$G$2:$G$37,"")+COUNTIFS(Captura_Fin!$A$2:$A$37,$A20,Captura_Fin!$H$2:$H$37,"")+COUNTIFS(Captura_Fin!$A$2:$A$37,$A20,Captura_Fin!$I$2:$I$37,"")+COUNTIFS(Captura_Fin!$A$2:$A$37,$A20,Captura_Fin!$J$2:$J$37,"")+COUNTIFS(Captura_Fin!$A$2:$A$37,$A20,Captura_Fin!$L$2:$L$37,"")+COUNTIFS(Captura_Fin!$A$2:$A$37,$A20,Captura_Fin!$M$2:$M$37,"")+COUNTIFS(Captura_Fin!$A$2:$A$37,$A20,Captura_Fin!$N$2:$N$37,"")+COUNTIFS(Captura_Fin!$A$2:$A$37,$A20,Captura_Fin!$O$2:$O$37,"")+COUNTIFS(Captura_Fin!$A$2:$A$37,$A20,Captura_Fin!$P$2:$P$37,"")+COUNTIFS(Captura_Fin!$A$2:$A$37,$A20,Captura_Fin!$Q$2:$Q$37,"") | E20: =COUNTIFS(Ratios_Fin!$A$2:$A$37,$A20,Ratios_Fin!$N$2:$N$37,"REVISAR") | F20: =IFERROR(AVERAGEIFS(Ratios_Fin!$M$2:$M$37,Ratios_Fin!$A$2:$A$37,$A20),0) | G20: =IF(D20=0,IF(E20=0,"COMPLETA","REVISAR CUADRE"),"PENDIENTE")
A21: BCI | B21: Financiera | C21: =COUNTIFS(Captura_Fin!$A$2:$A$37,$A21,Captura_Fin!$F$2:$F$37,"<>") | D21: =COUNTIFS(Captura_Fin!$A$2:$A$37,$A21,Captura_Fin!$F$2:$F$37,"")+COUNTIFS(Captura_Fin!$A$2:$A$37,$A21,Captura_Fin!$G$2:$G$37,"")+COUNTIFS(Captura_Fin!$A$2:$A$37,$A21,Captura_Fin!$H$2:$H$37,"")+COUNTIFS(Captura_Fin!$A$2:$A$37,$A21,Captura_Fin!$I$2:$I$37,"")+COUNTIFS(Captura_Fin!$A$2:$A$37,$A21,Captura_Fin!$J$2:$J$37,"")+COUNTIFS(Captura_Fin!$A$2:$A$37,$A21,Captura_Fin!$L$2:$L$37,"")+COUNTIFS(Captura_Fin!$A$2:$A$37,$A21,Captura_Fin!$M$2:$M$37,"")+COUNTIFS(Captura_Fin!$A$2:$A$37,$A21,Captura_Fin!$N$2:$N$37,"")+COUNTIFS(Captura_Fin!$A$2:$A$37,$A21,Captura_Fin!$O$2:$O$37,"")+COUNTIFS(Captura_Fin!$A$2:$A$37,$A21,Captura_Fin!$P$2:$P$37,"")+COUNTIFS(Captura_Fin!$A$2:$A$37,$A21,Captura_Fin!$Q$2:$Q$37,"") | E21: =COUNTIFS(Ratios_Fin!$A$2:$A$37,$A21,Ratios_Fin!$N$2:$N$37,"REVISAR") | F21: =IFERROR(AVERAGEIFS(Ratios_Fin!$M$2:$M$37,Ratios_Fin!$A$2:$A$37,$A21),0) | G21: =IF(D21=0,IF(E21=0,"COMPLETA","REVISAR CUADRE"),"PENDIENTE")
A22: BSANTANDER | B22: Financiera | C22: =COUNTIFS(Captura_Fin!$A$2:$A$37,$A22,Captura_Fin!$F$2:$F$37,"<>") | D22: =COUNTIFS(Captura_Fin!$A$2:$A$37,$A22,Captura_Fin!$F$2:$F$37,"")+COUNTIFS(Captura_Fin!$A$2:$A$37,$A22,Captura_Fin!$G$2:$G$37,"")+COUNTIFS(Captura_Fin!$A$2:$A$37,$A22,Captura_Fin!$H$2:$H$37,"")+COUNTIFS(Captura_Fin!$A$2:$A$37,$A22,Captura_Fin!$I$2:$I$37,"")+COUNTIFS(Captura_Fin!$A$2:$A$37,$A22,Captura_Fin!$J$2:$J$37,"")+COUNTIFS(Captura_Fin!$A$2:$A$37,$A22,Captura_Fin!$L$2:$L$37,"")+COUNTIFS(Captura_Fin!$A$2:$A$37,$A22,Captura_Fin!$M$2:$M$37,"")+COUNTIFS(Captura_Fin!$A$2:$A$37,$A22,Captura_Fin!$N$2:$N$37,"")+COUNTIFS(Captura_Fin!$A$2:$A$37,$A22,Captura_Fin!$O$2:$O$37,"")+COUNTIFS(Captura_Fin!$A$2:$A$37,$A22,Captura_Fin!$P$2:$P$37,"")+COUNTIFS(Captura_Fin!$A$2:$A$37,$A22,Captura_Fin!$Q$2:$Q$37,"") | E22: =COUNTIFS(Ratios_Fin!$A$2:$A$37,$A22,Ratios_Fin!$N$2:$N$37,"REVISAR") | F22: =IFERROR(AVERAGEIFS(Ratios_Fin!$M$2:$M$37,Ratios_Fin!$A$2:$A$37,$A22),0) | G22: =IF(D22=0,IF(E22=0,"COMPLETA","REVISAR CUADRE"),"PENDIENTE")
A23: ITAUCL | B23: Financiera | C23: =COUNTIFS(Captura_Fin!$A$2:$A$37,$A23,Captura_Fin!$F$2:$F$37,"<>") | D23: =COUNTIFS(Captura_Fin!$A$2:$A$37,$A23,Captura_Fin!$F$2:$F$37,"")+COUNTIFS(Captura_Fin!$A$2:$A$37,$A23,Captura_Fin!$G$2:$G$37,"")+COUNTIFS(Captura_Fin!$A$2:$A$37,$A23,Captura_Fin!$H$2:$H$37,"")+COUNTIFS(Captura_Fin!$A$2:$A$37,$A23,Captura_Fin!$I$2:$I$37,"")+COUNTIFS(Captura_Fin!$A$2:$A$37,$A23,Captura_Fin!$J$2:$J$37,"")+COUNTIFS(Captura_Fin!$A$2:$A$37,$A23,Captura_Fin!$L$2:$L$37,"")+COUNTIFS(Captura_Fin!$A$2:$A$37,$A23,Captura_Fin!$M$2:$M$37,"")+COUNTIFS(Captura_Fin!$A$2:$A$37,$A23,Captura_Fin!$N$2:$N$37,"")+COUNTIFS(Captura_Fin!$A$2:$A$37,$A23,Captura_Fin!$O$2:$O$37,"")+COUNTIFS(Captura_Fin!$A$2:$A$37,$A23,Captura_Fin!$P$2:$P$37,"")+COUNTIFS(Captura_Fin!$A$2:$A$37,$A23,Captura_Fin!$Q$2:$Q$37,"") | E23: =COUNTIFS(Ratios_Fin!$A$2:$A$37,$A23,Ratios_Fin!$N$2:$N$37,"REVISAR") | F23: =IFERROR(AVERAGEIFS(Ratios_Fin!$M$2:$M$37,Ratios_Fin!$A$2:$A$37,$A23),0) | G23: =IF(D23=0,IF(E23=0,"COMPLETA","REVISAR CUADRE"),"PENDIENTE")
A25: Empresas completas: | C25: =COUNTIF(G2:G23,"COMPLETA")&" de 22"
A26: Tolerancia de cuadre: |Activo − Pasivo − Patrimonio| ≤ 0,5% del activo total.

Sheet Fase3_KPI
A1: nemotecnico | B1: sector | C1: anio | D1: F1_liquidez | E1: F2_capital_trabajo | F1: F3_eficiencia | G1: F4_rentabilidad_ROA | H1: F5_endeudamiento | I1: F6_cobertura | J1: F7_uso_activos | K1: F8_mercado_retorno | L1: EBIT | M1: z_F1_liquidez | N1: z_F2_capital_trabajo | O1: z_F3_eficiencia | P1: z_F4_rentabilidad_ROA | Q1: z_F5_endeudamiento | R1: z_F6_cobertura | S1: z_F7_uso_activos | T1: z_F8_mercado_retorno | U1: n_familias | V1: KPI | W1: KPI_PCA
A2: ANDINA-B | B2: Consumo | C2: 2017 | D2: 1.1301059 | E2: 0.026348194 | F2: 0.12224639 | G2: 0.056268857 | H2: 0.61546696 | I2: 4.0930318 | J2: 0.87423238 | K2: 0.26974991 | L2: 226018728 | M2: -0.72528481 | N2: -0.66354394 | O2: 0.55456637 | P2: 0.74299693 | Q2: -0.051047209 | R2: -0.13390884 | S2: 0.89107395 | T2: 0.59915096 | U2: 8 | V2: 0.15175042 | W2: 0.041418909
A3: ANDINA-B | B3: Consumo | C3: 2018 | D3: 1.147011 | E3: 0.027872758 | F3: 0.1243519 | G3: 0.044005663 | H3: 0.60997385 | I3: 3.7813605 | J3: 0.75543565 | K3: -0.12498555 | L3: 208030261 | M3: -0.68311256 | N3: -0.64783096 | O3: 0.59631262 | P3: 0.24210658 | Q3: 0.0081433531 | R3: -0.23968979 | S3: 0.30716155 | T3: -0.76406234 | U3: 8 | V3: -0.14762144 | W3: -0.10173661
A4: ANDINA-B | B4: Consumo | C4: 2019 | D4: 1.2959147 | E4: 0.050948716 | F4: 0.15886349 | G4: 0.073295694 | H4: 0.59476167 | I4: 6.1161681 | J4: 0.74406671 | K4: -0.12647986 | L4: 282622136 | M4: -0.31164976 | N4: -0.4099975 | O4: 1.2805768 | P4: 1.4384583 | Q4: 0.17206101 | R4: 0.55274163 | S4: 0.25128063 | T4: -0.76922292 | U4: 8 | V4: 0.27553102 | W4: 0.44673829
A5: ANDINA-B | B5: Consumo | C5: 2020 | D5: 2.1089397 | E5: 0.17125429 | F5: 0.13707715 | G5: 0.0502917 | H5: 0.66031915 | I5: 4.2502008 | J5: 0.69372409 | K5: -0.10965187 | L5: 232795556 | M5: 1.7165646 | N5: 0.82993765 | O5: 0.84861724 | P5: 0.49885986 | Q5: -0.5343486 | R5: -0.080565845 | S5: 0.0038354149 | T5: -0.71110768 | U5: 8 | V5: 0.32147408 | W5: 0.4639829
A6: ANDINA-B | B6: Consumo | C6: 2021 | D6: 1.871313 | E6: 0.15661987 | F6: 0.11557616 | G6: 0.05330142 | H6: 0.62614607 | I6: 4.8346777 | J6: 0.75242782 | K6: 0.082968078 | L6: 256201444 | M6: 1.1237686 | N6: 0.67910732 | O6: 0.42231527 | P6: 0.62179192 | Q6: -0.16611914 | R6: 0.11780503 | S6: 0.29237736 | T6: -0.045897431 | U6: 8 | V6: 0.38064361 | W6: 0.43245259
A7: ANDINA-B | B7: Consumo | C7: 2022 | D7: 1.2238455 | E7: 0.070576349 | F7: 0.11003574 | G7: 0.042667473 | H7: 0.70657904 | I7: 4.9095152 | J7: 0.88247845 | K7: 0.21178269 | L7: 292351578 | M7: -0.49143726 | N7: -0.20770435 | O7: 0.31246485 | P7: 0.18744822 | Q7: -1.0328185 | R7: 0.1432048 | S7: 0.93160522 | T7: 0.398962 | U7: 8 | V7: 0.030215623 | W7: -0.095513254
A8: ANDINA-B | B8: Consumo | C8: 2023 | D8: 1.4169602 | E8: 0.098886759 | F8: 0.12442313 | G8: 0.059733096 | H8: 0.68475823 | I8: 4.9900807 | J8: 0.8962582 | K8: 0.13238977 | L8: 325794146 | M8: -0.0096834403 | N8: 0.084078236 | O8: 0.59772496 | P8: 0.8844938 | Q8: -0.79769 | R8: 0.17054866 | S8: 0.99933579 | T8: 0.12477967 | U8: 8 | V8: 0.25669846 | W8: 0.21052485
A9: ANDINA-B | B9: Consumo | C9: 2024 | D9: 1.1181399 | E9: 0.032527607 | F9: 0.13598603 | G9: 0.071296472 | H9: 0.69177609 | I9: 6.2267643 | J9: 0.97968121 | K9: 0.44945095 | L9: 438450654 | M9: -0.75513598 | N9: -0.59985553 | O9: 0.82698352 | P9: 1.3568001 | Q9: -0.87331043 | R9: 0.59027786 | S9: 1.4093785 | T9: 1.219746 | U9: 8 | V9: 0.39686049 | W9: 0.23044957
A10: ANDINA-B | B10: Consumo | C10: 2025 | D10: 1.4143416 | E10: 0.088480816 | F10: 0.13419276 | G10: 0.079077589 | H10: 0.65017192 | I10: 6.5796423 | J10: 0.97790625 | K10: 0.48863363 | L10: 448852755 | M10: -0.016215944 | N10: -0.023171104 | O10: 0.79142815 | P10: 1.6746199 | Q10: -0.42500792 | R10: 0.71004429 | S10: 1.4006542 | T10: 1.3550628 | U10: 8 | V10: 0.68342679 | W10: 0.55524478
A11: CCU | B11: Consumo | C11: 2017 | D11: 1.5554291 | E11: 0.13174439 | F11: 0.12991392 | G11: 0.074944965 | H11: 0.37920729 | I11: 9.1300939 | J11: 0.8593947 | K11: 0.34894183 | L11: 220640708 | M11: 0.33574838 | N11: 0.422727 | O11: 0.70659122 | P11: 1.5058228 | Q11: 2.4505252 | R11: 1.5756651 | S11: 0.81814344 | T11: 0.87263914 | U11: 8 | V11: 1.0859828 | W11: 1.1606968
A12: CCU | B12: Consumo | C12: 2018 | D12: 1.4572897 | E12: 0.12273466 | F12: 0.27016025 | G12: 0.13387474 | H12: 0.42261266 | I12: 20.448153 | J12: 0.74122297 | K12: -0.013889199 | L12: 481772010 | M12: 0.090924575 | N12: 0.32986778 | O12: 3.013403 | P12: 2.7265693 | Q12: 2.0270394 | R12: 3.7068407 | S12: 0.23730303 | T12: -0.38039266 | U12: 8 | V12: 1.4689444 | W12: 1.912801
A13: CCU | B13: Consumo | C13: 2019 | D13: 1.6331702 | E13: 0.13000848 | F13: 0.11705735 | G13: 0.061879694 | H13: 0.38695122 | I13: 7.6962559 | J13: 0.77433313 | K13: -0.11896119 | L13: 213341777 | M13: 0.52968531 | N13: 0.40483579 | O13: 0.45168284 | P13: 0.97217162 | Q13: 2.4113065 | R13: 1.0890219 | S13: 0.40004686 | T13: -0.74325729 | U13: 8 | V13: 0.68943669 | W13: 0.90254389
... A55: RIPLEY | B55: Consumo | C55: 2025 | D55: 0.83262169 | E55: -0.076697436 | F55: 0.08821902 | G55: 0.028885761 | H55: 0.71929681 | I55: 3.6956523 | J55: 0.53803563 | K55: 0.5637871 | L55: 195829054 | M55: -1.4674044 | N55: -1.718238 | O55: -0.12009708 | P55: -0.375466 | Q55: -1.1698578 | R55: -0.26877905 | S55: -0.76140808 | T55: 1.6146042 | U55: 8 | V55: -0.53333078 | W55: -0.7424494
A56: BCI | B56: Financiero (bancos) | C56: 2017 | D56: 0.073949236 | F56: 0.53712677 | G56: 0.010961859 | H56: 0.91948015 | I56: 3.5345469 | J56: 0.040748631 | K56: 0.31147467 | M56: -0.79353415 | O56: -0.30360444 | P56: -0.02386508 | Q56: -0.17557614 | R56: 0.46096564 | S56: 0.027032548 | T56: 0.47782304 | U56: 7 | V56: -0.047251227 | W56: -0.010966348
A57: BCI | B57: Financiero (bancos) | C57: 2018 | D57: 0.083855264 | F57: 0.54521534 | G57: 0.009573149 | H57: 0.91636308 | I57: 2.9512716 | J57: 0.03833649 | K57: 0.093369461 | M57: -0.51505434 | O57: -0.35874181 | P57: -0.21878511 | Q57: 0.017631656 | R57: -0.036515519 | S57: -0.27264097 | T57: -0.1804737 | U57: 7 | V57: -0.2235114 | W57: -0.22863651
A58: BCI | B58: Financiero (bancos) | C58: 2019 | D58: 0.11445969 | F58: 0.50625704 | G58: 0.0080009146 | H58: 0.92465684 | I58: 2.2783435 | J58: 0.037582738 | K58: -0.19371685 | M58: 0.34530215 | O58: -0.093174942 | P58: -0.43946475 | Q58: -0.49644712 | R58: -0.6104625 | S58: -0.36628368 | T58: -1.0469728 | U58: 7 | V58: -0.38678624 | W58: -0.38813393
A59: BCI | B59: Financiero (bancos) | C59: 2020 | D59: 0.15042332 | F59: 0.50969184 | G59: 0.0055555207 | H59: 0.93185869 | I59: 1.5233097 | J59: 0.035557376 | K59: -0.11044872 | M59: 1.3563172 | O59: -0.11658891 | P59: -0.78270153 | Q59: -0.94284519 | R59: -1.2544381 | S59: -0.61790552 | T59: -0.79564855 | U59: 7 | V59: -0.45054437 | W59: -0.50889125
A60: BCI | B60: Financiero (bancos) | C60: 2021 | D60: 0.1028204 | F60: 0.48166314 | G60: 0.0075268259 | H60: 0.93491086 | I60: 2.8026139 | J60: 0.031251384 | K60: -0.047540183 | M60: 0.018096648 | O60: 0.074474174 | P60: -0.50600809 | Q60: -1.1320302 | R60: -0.16330711 | S60: -1.1528625 | T60: -0.60577467 | U60: 7 | V60: -0.49534453 | W60: -0.44782112
A61: BCI | B61: Financiero (bancos) | C61: 2022 | D61: 0.10046222 | F61: 0.47879699 | G61: 0.010519324 | H61: 0.93879751 | I61: 2.8427127 | J61: 0.034581921 | K61: 0.10001933 | M61: -0.048196932 | O61: 0.094011899 | P61: -0.085979546 | Q61: -1.3729393 | R61: -0.12910651 | S61: -0.73909164 | T61: -0.16040269 | U61: 7 | V61: -0.34881496 | W61: -0.26326898
A62: BCI | B62: Financiero (bancos) | C62: 2023 | D62: 0.085668518 | F62: 0.51703522 | G62: 0.00860733 | H62: 0.92348944 | I62: 3.0487496 | J62: 0.031781771 | K62: 0.30163271 | M62: -0.46407987 | O62: -0.16664647 | P62: -0.35434797 | Q62: -0.42408744 | R62: 0.04662438 | S62: -1.0869696 | T62: 0.44811751 | U62: 7 | V62: -0.28591278 | W62: -0.29297973
A63: BCI | B63: Financiero (bancos) | C63: 2024 | D63: 0.072594218 | F63: 0.48867547 | G63: 0.009610896 | H63: 0.91611149 | I63: 4.3543855 | J63: 0.032809397 | K63: 0.19945199 | M63: -0.83162664 | O63: 0.026673264 | P63: -0.21348691 | Q63: 0.033226185 | R63: 1.160214 | S63: -0.95930201 | T63: 0.13971022 | U63: 7 | V63: -0.09208456 | W63: -0.050563058
A64: BCI | B64: Financiero (bancos) | C64: 2025 | D64: 0.072127582 | F64: 0.51662429 | G64: 0.012213637 | H64: 0.90870803 | I64: 4.7349836 | J64: 0.037505591 | K64: 1.1852476 | M64: -0.84474478 | O64: -0.16384529 | P64: 0.15183517 | Q64: 0.49212082 | R64: 1.4848298 | S64: -0.37586803 | T64: 2.9614636 | U64: 7 | V64: 0.52939876 | W64: 0.49403897
A65: BSANTANDER | B65: Financiero (bancos) | C65: 2017 | D65: 0.073819419 | F65: 0.44251096 | G65: 0.016122738 | H65: 0.91319297 | I65: 3.4093047 | J65: 0.050906457 | K65: 0.3514782 | M65: -0.79718358 | O65: 0.34136273 | P65: 0.70051861 | Q65: 0.21412685 | R65: 0.35414532 | S65: 1.2889949 | T65: 0.59856381 | U65: 7 | V65: 0.38578981 | W65: 0.45896413
A66: BSANTANDER | B66: Financiero (bancos) | C66: 2018 | D66: 0.094704876 | F66: 0.41501064 | G66: 0.015211791 | H66: 0.91617524 | I66: 3.3444914 | J66: 0.047193515 | K66: 0.12095707 | M66: -0.21004834 | O66: 0.52882399 | P66: 0.57265769 | Q66: 0.029274716 | R66: 0.2988655 | S66: 0.82771576 | T66: -0.097207317 | U66: 7 | V66: 0.27858314 | W66: 0.35419429
A67: BSANTANDER | B67: Financiero (bancos) | C67: 2019 | D67: 0.15131896 | F67: 0.4203489 | G67: 0.010956805 | H67: 0.93138716 | I67: 2.6711857 | J67: 0.038268508 | K67: -0.13629518 | M67: 1.3814956 | O67: 0.49243469 | P67: -0.024574364 | Q67: -0.913618 | R67: -0.27540356 | S67: -0.28108674 | T67: -0.87365972 | U67: 7 | V67: -0.070630304 | W67: -0.028947781
... A91: ITAUCL | B91: Financiero (bancos) | C91: 2025 | D91: 0.13481313 | F91: 0.54987857 | G91: 0.009748288 | H91: 0.90188712 | I91: 2.1399419 | J91: 0.034568799 | K91: 1.0398206 | M91: 0.91748112 | O91: -0.39052958 | P91: -0.19420251 | Q91: 0.91490683 | R91: -0.72850654 | S91: -0.74072181 | T91: 2.6761555 | U91: 7 | V91: 0.35065472 | W91: 0.11361626
A92: CAP | B92: Industria, recursos naturales e inmobiliario | C92: 2017 | D92: 1.2609484 | E92: 0.050088094 | F92: 0.1923635 | G92: 0.034609474 | H92: 0.41196126 | I92: 4.0574586 | J92: 0.34802527 | K92: 0.71094744 | L92: 371578 | M92: -0.60453851 | N92: -0.23570926 | O92: -0.13960203 | P92: 0.052592758 | Q92: 0.90840582 | R92: -0.16869655 | S92: -0.46782006 | T92: 1.4721118 | U92: 8 | V92: 0.102093 | W92: -0.0001980246
A93: CAP | B93: Industria, recursos naturales e inmobiliario | C93: 2018 | D93: 1.3732154 | E93: 0.060986224 | F93: 0.17273075 | G93: 0.032662452 | H93: 0.37428337 | I93: 4.2377723 | J93: 0.35891405 | K93: -0.19219497 | L93: 331148 | M93: -0.50031129 | N93: -0.17448607 | O93: -0.19520717 | P93: 0.029216397 | Q93: 1.0112116 | R93: -0.14341876 | S93: -0.43064094 | T93: -0.73609468 | U93: 8 | V93: -0.14246636 | W93: -0.033967779
A94: CAP | B94: Industria, recursos naturales e inmobiliario | C94: 2019 | D94: 1.0841356 | E94: 0.017580883 | F94: -0.014024219 | G94: -0.016313985 | H94: 0.4080285 | I94: -0.22651053 | J94: 0.29025843 | K94: -0.043017134 | L94: -22302 | M94: -0.76868912 | N94: -0.41832729 | O94: -0.72414664 | P94: -0.55880518 | Q94: 0.92883283 | R94: -0.76925706 | S94: -0.66506164 | T94: -0.37135102 | U94: 8 | V94: -0.41835064 | W94: -0.40481222
A95: CAP | B95: Industria, recursos naturales e inmobiliario | C95: 2020 | D95: 0.9540482 | E95: -0.01219429 | F95: 0.26356372 | G95: 0.07364902 | H95: 0.41196822 | I95: 8.280129 | J95: 0.4566855 | K95: 0.73060932 | L95: 706088 | M95: -0.88946056 | N95: -0.58559737 | O95: 0.062055814 | P95: 0.5213099 | Q95: 0.90836971 | R95: 0.42327062 | S95: -0.096805907 | T95: 1.5201856 | U95: 8 | V95: 0.23291598 | W95: 0.13447221
A96: CAP | B96: Industria, recursos naturales e inmobiliario | C96: 2021 | D96: 1.2241853 | E96: 0.054926832 | F96: 0.4181229 | G96: 0.15019852 | H96: 0.44538229 | I96: 24.26473 | J96: 0.55606365 | K96: -0.0047756605 | L96: 1537389 | M96: -0.63866888 | N96: -0.20852634 | O96: 0.49980829 | P96: 1.4403796 | Q96: 0.73481515 | R96: 2.6641177 | S96: 0.24251509 | T96: -0.27784963 | U96: 8 | V96: 0.55707388 | W96: 0.75368207
A97: CAP | B97: Industria, recursos naturales e inmobiliario | C97: 2022 | D97: 1.1339102 | E97: 0.030346523 | F97: 0.19634124 | G97: 0.051052095 | H97: 0.43615871 | I97: 7.3141869 | J97: 0.45810584 | K97: 0.036683772 | L97: 590211 | M97: -0.7224791 | N97: -0.34661286 | O97: -0.12833603 | P97: 0.25000638 | Q97: 0.78272294 | R97: 0.28785726 | S97: -0.091956239 | T97: -0.17648025 | U97: 8 | V97: -0.018159737 | W97: 0.025835394
A98: CAP | B98: Industria, recursos naturales e inmobiliario | C98: 2023 | D98: 1.4291291 | E98: 0.086355605 | F98: 0.27093307 | G98: 0.012555555 | H98: 0.47747219 | I98: 7.3504085 | J98: 0.34264544 | K98: 0.082899585 | L98: 650445 | M98: -0.44840181 | N98: -0.03196672 | O98: 0.082927751 | P98: -0.21219131 | Q98: 0.56813839 | R98: 0.29293509 | S98: -0.48618917 | T98: -0.063481391 | U98: 8 | V98: -0.037278647 | W98: 0.021846681
A99: CAP | B99: Industria, recursos naturales e inmobiliario | C99: 2024 | D99: 1.1192974 | E99: 0.021635141 | F99: 0.10958622 | G99: -0.064197876 | H99: 0.49872785 | I99: 1.6211566 | J99: 0.28342226 | K99: -0.26944444 | L99: 197405 | M99: -0.73604543 | N99: -0.39555141 | O99: -0.37404919 | P99: -1.1337094 | Q99: 0.45773531 | R99: -0.51023654 | S99: -0.68840333 | T99: -0.92497163 | U99: 8 | V99: -0.53815395 | W99: -0.48207678
A100: CAP | B100: Industria, recursos naturales e inmobiliario | C100: 2025 | D100: 1.1665099 | E100: 0.027748003 | F100: 0.029177221 | G100: -0.01610716 | H100: 0.50660064 | I100: 0.43490315 | J100: 0.31555957 | K100: 0.41064639 | L100: 56313 | M100: -0.692214 | N100: -0.36121075 | O100: -0.60178874 | P100: -0.556322 | Q100: 0.41684358 | R100: -0.67653488 | S100: -0.57867234 | T100: 0.73786799 | U100: 8 | V100: -0.28900389 | W100: -0.39037805
A101: CMPC | B101: Industria, recursos naturales e inmobiliario | C101: 2017 | D101: 2.3220037 | E101: 0.12816002 | F101: 0.065835335 | G101: 0.0068613715 | H101: 0.45926095 | I101: 1.542684 | J101: 0.3439999 | K101: 0.52830028 | L101: 338596 | M101: 0.38053103 | N101: 0.20288089 | O101: -0.49796326 | P101: -0.2805569 | Q101: 0.66272862 | R101: -0.52123744 | S101: -0.48156446 | T101: 1.0255348 | U101: 8 | V101: 0.061294157 | W101: -0.021661753
A102: CMPC | B102: Industria, recursos naturales e inmobiliario | C102: 2018 | D102: 2.2757944 | E102: 0.14054317 | F102: 0.17470267 | G102: 0.033524633 | H102: 0.44978663 | I102: 5.0755522 | J102: 0.41876405 | K102: 0.067417937 | L102: 1096167 | M102: 0.33763092 | N102: 0.27244655 | O102: -0.18962219 | P102: 0.039567919 | Q102: 0.71193873 | R102: -0.025972182 | S102: -0.22628653 | T102: -0.10133442 | U102: 8 | V102: 0.1022961 | W102: 0.15230488
A103: CMPC | B103: Industria, recursos naturales e inmobiliario | C103: 2019 | D103: 2.2649603 | E103: 0.12899033 | F103: 0.073472954 | G103: 0.0056426953 | H103: 0.45602528 | I103: 2.132644 | J103: 0.37913575 | K103: -0.13807852 | L103: 416612 | M103: 0.32757269 | N103: 0.20754534 | O103: -0.47633151 | P103: -0.29518859 | Q103: 0.67953486 | R103: -0.43853221 | S103: -0.36159508 | T103: -0.60377856 | U103: 8 | V103: -0.12009663 | W103: -0.05420422
... A199: ENTEL | B199: Servicios básicos e infraestructura | C199: 2025 | D199: 1.1577891 | E199: 0.032180358 | F199: 0.086132652 | G199: 0.033479184 | H199: 0.66007735 | I199: 1.5391395 | J199: 0.51687816 | K199: 0.70447473 | L199: 254515981 | M199: -0.33918898 | N199: 0.027756918 | O199: -0.94661034 | P199: -0.091259201 | Q199: -0.90686094 | R199: -0.76616826 | S199: 1.8174941 | T199: 2.2565353 | U199: 8 | V199: 0.13146232 | W199: -0.32572308

Sheet Fase5_Pesos
A1: bloque | B1: familia | C1: peso_igual | D1: peso_pca
A2: No financieras | B2: F1_liquidez | C2: 0.125 | D2: 0.13718966
A3: No financieras | B3: F2_capital_trabajo | C3: 0.125 | D3: 0.14850422
A4: No financieras | B4: F3_eficiencia | C4: 0.125 | D4: 0.16005515
A5: No financieras | B5: F4_rentabilidad_ROA | C5: 0.125 | D5: 0.16720355
A6: No financieras | B6: F5_endeudamiento | C6: 0.125 | D6: 0.14931702
A7: No financieras | B7: F6_cobertura | C7: 0.125 | D7: 0.16496931
A8: No financieras | B8: F7_uso_activos | C8: 0.125 | D8: 0.043110073
A9: No financieras | B9: F8_mercado_retorno | C9: 0.125 | D9: 0.029651016
A10: Bancos | B10: F1_liquidez | C10: 0.14285714 | D10: 0.11193011
A11: Bancos | B11: F3_eficiencia | C11: 0.14285714 | D11: 0.16260414
A12: Bancos | B12: F4_rentabilidad_ROA | C12: 0.14285714 | D12: 0.1963679
A13: Bancos | B13: F5_endeudamiento | C13: 0.14285714 | D13: 0.069671401
... A16: Bancos | B16: F8_mercado_retorno | C16: 0.14285714 | D16: 0.11321813
